{
"meta":{"test_sets":[],"test_metrics":[],"learn_metrics":[{"best_value":"Min","name":"Logloss"}],"launch_mode":"Train","parameters":"","iteration_count":1000,"learn_sets":["learn"],"name":"experiment"},
"iterations":[
{"learn":[0.6788024408],"iteration":0,"passed_time":0.003088770424,"remaining_time":3.085681654},
{"learn":[0.6671202225],"iteration":1,"passed_time":0.005958688504,"remaining_time":2.973385563},
{"learn":[0.6550317476],"iteration":2,"passed_time":0.009350295395,"remaining_time":3.107414836},
{"learn":[0.6425222043],"iteration":3,"passed_time":0.01226162356,"remaining_time":3.053144266},
{"learn":[0.6306338535],"iteration":4,"passed_time":0.01522788586,"remaining_time":3.030349285},
{"learn":[0.6203564316],"iteration":5,"passed_time":0.0180486272,"remaining_time":2.990055906},
{"learn":[0.6093938612],"iteration":6,"passed_time":0.02108114456,"remaining_time":2.990510935},
{"learn":[0.5983102094],"iteration":7,"passed_time":0.02476990297,"remaining_time":3.071467968},
{"learn":[0.5881667793],"iteration":8,"passed_time":0.02777388087,"remaining_time":3.058212883},
{"learn":[0.5787172864],"iteration":9,"passed_time":0.0306541451,"remaining_time":3.034760365},
{"learn":[0.5696054395],"iteration":10,"passed_time":0.03351186744,"remaining_time":3.013021537},
{"learn":[0.5605890812],"iteration":11,"passed_time":0.03642856927,"remaining_time":2.999285537},
{"learn":[0.5522292308],"iteration":12,"passed_time":0.03939837309,"remaining_time":2.991245711},
{"learn":[0.5443617761],"iteration":13,"passed_time":0.04257701653,"remaining_time":2.99863845},
{"learn":[0.5371314477],"iteration":14,"passed_time":0.04560949296,"remaining_time":2.995023371},
{"learn":[0.530204819],"iteration":15,"passed_time":0.04849285593,"remaining_time":2.98231064},
{"learn":[0.5239066482],"iteration":16,"passed_time":0.05144647905,"remaining_time":2.974816995},
{"learn":[0.5183248058],"iteration":17,"passed_time":0.05454765687,"remaining_time":2.975877725},
{"learn":[0.5124189868],"iteration":18,"passed_time":0.05772137881,"remaining_time":2.980245927},
{"learn":[0.5072727052],"iteration":19,"passed_time":0.06057871876,"remaining_time":2.968357219},
{"learn":[0.5017362192],"iteration":20,"passed_time":0.0633791019,"remaining_time":2.95467337},
{"learn":[0.4963449749],"iteration":21,"passed_time":0.06621927431,"remaining_time":2.94374774},
{"learn":[0.4921799143],"iteration":22,"passed_time":0.06909025974,"remaining_time":2.934834077},
{"learn":[0.4877610802],"iteration":23,"passed_time":0.07212752685,"remaining_time":2.933186092},
{"learn":[0.4841954575],"iteration":24,"passed_time":0.07518702322,"remaining_time":2.932293906},
{"learn":[0.4805915385],"iteration":25,"passed_time":0.07830389938,"remaining_time":2.933384538},
{"learn":[0.4761078567],"iteration":26,"passed_time":0.08142691299,"remaining_time":2.934384679},
{"learn":[0.4724305512],"iteration":27,"passed_time":0.08515011719,"remaining_time":2.955925497},
{"learn":[0.468946178],"iteration":28,"passed_time":0.0888728491,"remaining_time":2.975708154},
{"learn":[0.4654384328],"iteration":29,"passed_time":0.09260110528,"remaining_time":2.994102404},
{"learn":[0.4615956436],"iteration":30,"passed_time":0.0958831052,"remaining_time":2.997120288},
{"learn":[0.4587945014],"iteration":31,"passed_time":0.09895542188,"remaining_time":2.993401512},
{"learn":[0.4559357577],"iteration":32,"passed_time":0.1020943562,"remaining_time":2.991674014},
{"learn":[0.4525079138],"iteration":33,"passed_time":0.1056429563,"remaining_time":3.001502817},
{"learn":[0.4495260882],"iteration":34,"passed_time":0.1085860692,"remaining_time":2.993873051},
{"learn":[0.4468864715],"iteration":35,"passed_time":0.1115723318,"remaining_time":2.987659107},
{"learn":[0.4436500711],"iteration":36,"passed_time":0.1144843443,"remaining_time":2.979687122},
{"learn":[0.4413455303],"iteration":37,"passed_time":0.1175831563,"remaining_time":2.97671043},
{"learn":[0.4391440241],"iteration":38,"passed_time":0.1208959501,"remaining_time":2.979000206},
{"learn":[0.4363531412],"iteration":39,"passed_time":0.1239794763,"remaining_time":2.975507432},
{"learn":[0.4341791717],"iteration":40,"passed_time":0.1269604206,"remaining_time":2.969635204},
{"learn":[0.4318430569],"iteration":41,"passed_time":0.1300412204,"remaining_time":2.966178314},
{"learn":[0.4293787306],"iteration":42,"passed_time":0.1330369171,"remaining_time":2.960844876},
{"learn":[0.427273159],"iteration":43,"passed_time":0.1366150834,"remaining_time":2.968273175},
{"learn":[0.4254891918],"iteration":44,"passed_time":0.1396040982,"remaining_time":2.962709196},
{"learn":[0.4235489868],"iteration":45,"passed_time":0.1425143899,"remaining_time":2.955624521},
{"learn":[0.4218644915],"iteration":46,"passed_time":0.1456437838,"remaining_time":2.953160127},
{"learn":[0.4201781464],"iteration":47,"passed_time":0.1485417684,"remaining_time":2.946078406},
{"learn":[0.4182364514],"iteration":48,"passed_time":0.1516609788,"remaining_time":2.943461038},
{"learn":[0.4163450517],"iteration":49,"passed_time":0.154902737,"remaining_time":2.943152003},
{"learn":[0.4146299454],"iteration":50,"passed_time":0.1578682446,"remaining_time":2.937587531},
{"learn":[0.4132837566],"iteration":51,"passed_time":0.1608000812,"remaining_time":2.931509172},
{"learn":[0.4119108626],"iteration":52,"passed_time":0.1637503936,"remaining_time":2.925879674},
{"learn":[0.410358878],"iteration":53,"passed_time":0.1667572703,"remaining_time":2.921340328},
{"learn":[0.409085057],"iteration":54,"passed_time":0.1701716696,"remaining_time":2.923858688},
{"learn":[0.4079091402],"iteration":55,"passed_time":0.1732118047,"remaining_time":2.919856137},
{"learn":[0.4064041391],"iteration":56,"passed_time":0.1762736558,"remaining_time":2.916246622},
{"learn":[0.4052019505],"iteration":57,"passed_time":0.1792565423,"remaining_time":2.911373497},
{"learn":[0.4036389678],"iteration":58,"passed_time":0.1822164749,"remaining_time":2.906198354},
{"learn":[0.4025301029],"iteration":59,"passed_time":0.1856027893,"remaining_time":2.907777033},
{"learn":[0.4014445138],"iteration":60,"passed_time":0.1885190786,"remaining_time":2.901957619},
{"learn":[0.4001822301],"iteration":61,"passed_time":0.1916144591,"remaining_time":2.898941332},
{"learn":[0.3988558357],"iteration":62,"passed_time":0.1947359139,"remaining_time":2.896310339},
{"learn":[0.3977772899],"iteration":63,"passed_time":0.1976219134,"remaining_time":2.890220484},
{"learn":[0.396944539],"iteration":64,"passed_time":0.2007611191,"remaining_time":2.887871483},
{"learn":[0.396024031],"iteration":65,"passed_time":0.2039043497,"remaining_time":2.885555494},
{"learn":[0.3949446582],"iteration":66,"passed_time":0.207124261,"remaining_time":2.88428262},
{"learn":[0.3938843265],"iteration":67,"passed_time":0.2099280455,"remaining_time":2.877249094},
{"learn":[0.3930151605],"iteration":68,"passed_time":0.2130483025,"remaining_time":2.874608255},
{"learn":[0.3923358488],"iteration":69,"passed_time":0.2162226483,"remaining_time":2.872672328},
{"learn":[0.391231079],"iteration":70,"passed_time":0.2194472584,"remaining_time":2.871359198},
{"learn":[0.3900595989],"iteration":71,"passed_time":0.2225925925,"remaining_time":2.868971192},
{"learn":[0.3888024078],"iteration":72,"passed_time":0.2256978656,"remaining_time":2.866053718},
{"learn":[0.3877229096],"iteration":73,"passed_time":0.2287318723,"remaining_time":2.862239375},
{"learn":[0.3868526992],"iteration":74,"passed_time":0.231817805,"remaining_time":2.859086261},
{"learn":[0.3859774444],"iteration":75,"passed_time":0.2352031318,"remaining_time":2.859574919},
{"learn":[0.3851154242],"iteration":76,"passed_time":0.2382285246,"remaining_time":2.855648418},
{"learn":[0.3843153763],"iteration":77,"passed_time":0.2413449482,"remaining_time":2.852821055},
{"learn":[0.3835293919],"iteration":78,"passed_time":0.2443187075,"remaining_time":2.848323159},
{"learn":[0.3829921159],"iteration":79,"passed_time":0.2474946527,"remaining_time":2.846188506},
{"learn":[0.3820373618],"iteration":80,"passed_time":0.2513241226,"remaining_time":2.851442823},
{"learn":[0.3811879562],"iteration":81,"passed_time":0.2553389738,"remaining_time":2.858550951},
{"learn":[0.3805055057],"iteration":82,"passed_time":0.2582103316,"remaining_time":2.852757519},
{"learn":[0.3797475094],"iteration":83,"passed_time":0.2613664992,"remaining_time":2.850139444},
{"learn":[0.3789213295],"iteration":84,"passed_time":0.265061542,"remaining_time":2.853309541},
{"learn":[0.3782521648],"iteration":85,"passed_time":0.2684868896,"remaining_time":2.853453687},
{"learn":[0.3774237512],"iteration":86,"passed_time":0.2718794525,"remaining_time":2.853171726},
{"learn":[0.3766657908],"iteration":87,"passed_time":0.2748289296,"remaining_time":2.848227089},
{"learn":[0.3760938534],"iteration":88,"passed_time":0.2777718155,"remaining_time":2.843259819},
{"learn":[0.3752645094],"iteration":89,"passed_time":0.2809430723,"remaining_time":2.84064662},
{"learn":[0.3744174215],"iteration":90,"passed_time":0.2844059457,"remaining_time":2.840934117},
{"learn":[0.3737728145],"iteration":91,"passed_time":0.2880918871,"remaining_time":2.843341668},
{"learn":[0.3729030866],"iteration":92,"passed_time":0.2910647803,"remaining_time":2.83866404},
{"learn":[0.3723007561],"iteration":93,"passed_time":0.2939562239,"remaining_time":2.833237647},
{"learn":[0.3713820582],"iteration":94,"passed_time":0.2975610364,"remaining_time":2.834660399},
{"learn":[0.3706460596],"iteration":95,"passed_time":0.3006951807,"remaining_time":2.831546285},
{"learn":[0.3700056378],"iteration":96,"passed_time":0.3040023986,"remaining_time":2.830042948},
{"learn":[0.3695525829],"iteration":97,"passed_time":0.3068426616,"remaining_time":2.824204906},
{"learn":[0.369060187],"iteration":98,"passed_time":0.309873489,"remaining_time":2.820161754},
{"learn":[0.368489089],"iteration":99,"passed_time":0.3132720998,"remaining_time":2.819448898},
{"learn":[0.3679927752],"iteration":100,"passed_time":0.3169375616,"remaining_time":2.821058098},
{"learn":[0.3673641382],"iteration":101,"passed_time":0.3205050906,"remaining_time":2.82170168},
{"learn":[0.3668538411],"iteration":102,"passed_time":0.3235251603,"remaining_time":2.817495813},
{"learn":[0.3663621613],"iteration":103,"passed_time":0.3264823256,"remaining_time":2.812770805},
{"learn":[0.3657933402],"iteration":104,"passed_time":0.3299987746,"remaining_time":2.812846698},
{"learn":[0.3651962352],"iteration":105,"passed_time":0.3333175304,"remaining_time":2.811187474},
{"learn":[0.3645271587],"iteration":106,"passed_time":0.3371137866,"remaining_time":2.81348235},
{"learn":[0.3639657717],"iteration":107,"passed_time":0.340024994,"remaining_time":2.80835458},
{"learn":[0.3633448899],"iteration":108,"passed_time":0.343035423,"remaining_time":2.804078549},
{"learn":[0.3629301638],"iteration":109,"passed_time":0.346587526,"remaining_time":2.804208165},
{"learn":[0.3624120051],"iteration":110,"passed_time":0.3499350316,"remaining_time":2.802632821},
{"learn":[0.3618258547],"iteration":111,"passed_time":0.3529310402,"remaining_time":2.798238962},
{"learn":[0.3611589214],"iteration":112,"passed_time":0.3558125617,"remaining_time":2.79297117},
{"learn":[0.3606541419],"iteration":113,"passed_time":0.3589419204,"remaining_time":2.789671416},
{"learn":[0.3602277009],"iteration":114,"passed_time":0.3622154274,"remaining_time":2.787483941},
{"learn":[0.3596547023],"iteration":115,"passed_time":0.3653208918,"remaining_time":2.783997141},
{"learn":[0.359246113],"iteration":116,"passed_time":0.3681906897,"remaining_time":2.778738282},
{"learn":[0.3585640943],"iteration":117,"passed_time":0.3711629094,"remaining_time":2.774285475},
{"learn":[0.3580305819],"iteration":118,"passed_time":0.3743112218,"remaining_time":2.77116123},
{"learn":[0.3576805519],"iteration":119,"passed_time":0.377964196,"remaining_time":2.771737438},
{"learn":[0.3570048808],"iteration":120,"passed_time":0.3815861718,"remaining_time":2.772018553},
{"learn":[0.3565772178],"iteration":121,"passed_time":0.385174174,"remaining_time":2.771991186},
{"learn":[0.3560609647],"iteration":122,"passed_time":0.3888398075,"remaining_time":2.772459441},
{"learn":[0.355569011],"iteration":123,"passed_time":0.3924599863,"remaining_time":2.772539903},
{"learn":[0.3550373171],"iteration":124,"passed_time":0.396106107,"remaining_time":2.772742749},
{"learn":[0.354492371],"iteration":125,"passed_time":0.4002757277,"remaining_time":2.776515762},
{"learn":[0.3539760908],"iteration":126,"passed_time":0.4037234361,"remaining_time":2.775201258},
{"learn":[0.3535828075],"iteration":127,"passed_time":0.4067651913,"remaining_time":2.771087866},
{"learn":[0.3531384255],"iteration":128,"passed_time":0.4104315397,"remaining_time":2.771208303},
{"learn":[0.3527215754],"iteration":129,"passed_time":0.4145512129,"remaining_time":2.774304271},
{"learn":[0.3523338126],"iteration":130,"passed_time":0.4182165597,"remaining_time":2.774276262},
{"learn":[0.3518490837],"iteration":131,"passed_time":0.4216282775,"remaining_time":2.77252534},
{"learn":[0.3514155838],"iteration":132,"passed_time":0.4251851346,"remaining_time":2.771695577},
{"learn":[0.3510469302],"iteration":133,"passed_time":0.4285832416,"remaining_time":2.769799158},
{"learn":[0.3504569537],"iteration":134,"passed_time":0.4318979669,"remaining_time":2.767346232},
{"learn":[0.3500876672],"iteration":135,"passed_time":0.4349549267,"remaining_time":2.763243064},
{"learn":[0.3496848789],"iteration":136,"passed_time":0.437791104,"remaining_time":2.7577644},
{"learn":[0.349289949],"iteration":137,"passed_time":0.4408465708,"remaining_time":2.753693798},
{"learn":[0.3488556083],"iteration":138,"passed_time":0.4440230544,"remaining_time":2.750387409},
{"learn":[0.348416478],"iteration":139,"passed_time":0.4470029823,"remaining_time":2.745875463},
{"learn":[0.348019487],"iteration":140,"passed_time":0.4500198825,"remaining_time":2.74161049},
{"learn":[0.3474172331],"iteration":141,"passed_time":0.4530985483,"remaining_time":2.737736299},
{"learn":[0.3470547093],"iteration":142,"passed_time":0.4561494616,"remaining_time":2.733706913},
{"learn":[0.3466608336],"iteration":143,"passed_time":0.4596768786,"remaining_time":2.732523667},
{"learn":[0.3461673358],"iteration":144,"passed_time":0.4629493894,"remaining_time":2.72980502},
{"learn":[0.3456865833],"iteration":145,"passed_time":0.4662558428,"remaining_time":2.727277327},
{"learn":[0.3452748023],"iteration":146,"passed_time":0.469311314,"remaining_time":2.723282659},
{"learn":[0.3450209764],"iteration":147,"passed_time":0.4723938245,"remaining_time":2.719456341},
{"learn":[0.3447279311],"iteration":148,"passed_time":0.4760267633,"remaining_time":2.718783728},
{"learn":[0.3444085535],"iteration":149,"passed_time":0.4790680261,"remaining_time":2.714718814},
{"learn":[0.3439805144],"iteration":150,"passed_time":0.4820288436,"remaining_time":2.710215154},
{"learn":[0.3435682353],"iteration":151,"passed_time":0.4849100028,"remaining_time":2.705287384},
{"learn":[0.3430868417],"iteration":152,"passed_time":0.4878970352,"remaining_time":2.700972476},
{"learn":[0.3427471398],"iteration":153,"passed_time":0.4914094589,"remaining_time":2.699561054},
{"learn":[0.3423984588],"iteration":154,"passed_time":0.4944145954,"remaining_time":2.695356988},
{"learn":[0.3419826263],"iteration":155,"passed_time":0.4974129179,"remaining_time":2.691131428},
{"learn":[0.3415839446],"iteration":156,"passed_time":0.5004396389,"remaining_time":2.687073985},
{"learn":[0.3410194897],"iteration":157,"passed_time":0.5034574046,"remaining_time":2.682981865},
{"learn":[0.3407023497],"iteration":158,"passed_time":0.5072848008,"remaining_time":2.683185644},
{"learn":[0.3403361199],"iteration":159,"passed_time":0.5107578636,"remaining_time":2.681478784},
{"learn":[0.3399914395],"iteration":160,"passed_time":0.5136949274,"remaining_time":2.676956795},
{"learn":[0.339636052],"iteration":161,"passed_time":0.5165944271,"remaining_time":2.672260061},
{"learn":[0.3393284995],"iteration":162,"passed_time":0.5194137086,"remaining_time":2.667173461},
{"learn":[0.3389855982],"iteration":163,"passed_time":0.5230616758,"remaining_time":2.666338787},
{"learn":[0.3386078219],"iteration":164,"passed_time":0.5259108647,"remaining_time":2.661427709},
{"learn":[0.3383009641],"iteration":165,"passed_time":0.5287956063,"remaining_time":2.656720094},
{"learn":[0.337920244],"iteration":166,"passed_time":0.5317785438,"remaining_time":2.652524113},
{"learn":[0.3375690527],"iteration":167,"passed_time":0.5347688114,"remaining_time":2.648378876},
{"learn":[0.3371206478],"iteration":168,"passed_time":0.5381887005,"remaining_time":2.646359823},
{"learn":[0.3369110978],"iteration":169,"passed_time":0.5410576029,"remaining_time":2.641634179},
{"learn":[0.3364888077],"iteration":170,"passed_time":0.5441083602,"remaining_time":2.637811875},
{"learn":[0.336065012],"iteration":171,"passed_time":0.5471764245,"remaining_time":2.634081858},
{"learn":[0.3357972798],"iteration":172,"passed_time":0.5505852896,"remaining_time":2.631988639},
{"learn":[0.3355114326],"iteration":173,"passed_time":0.5540863226,"remaining_time":2.63031783},
{"learn":[0.3352705102],"iteration":174,"passed_time":0.5573175498,"remaining_time":2.627354163},
{"learn":[0.335003158],"iteration":175,"passed_time":0.5603153497,"remaining_time":2.623294592},
{"learn":[0.3345438395],"iteration":176,"passed_time":0.5632404642,"remaining_time":2.618909051},
{"learn":[0.3341471808],"iteration":177,"passed_time":0.5664956206,"remaining_time":2.616064046},
{"learn":[0.3337664268],"iteration":178,"passed_time":0.569709323,"remaining_time":2.613024325},
{"learn":[0.333455776],"iteration":179,"passed_time":0.5731981288,"remaining_time":2.61123592},
{"learn":[0.3330706354],"iteration":180,"passed_time":0.5762094635,"remaining_time":2.607268235},
{"learn":[0.3328685477],"iteration":181,"passed_time":0.5791490389,"remaining_time":2.602988538},
{"learn":[0.3325337674],"iteration":182,"passed_time":0.5823806435,"remaining_time":2.600027244},
{"learn":[0.3321048513],"iteration":183,"passed_time":0.5855223951,"remaining_time":2.596664535},
{"learn":[0.3319102728],"iteration":184,"passed_time":0.5884954701,"remaining_time":2.592561125},
{"learn":[0.3314867917],"iteration":185,"passed_time":0.5914852695,"remaining_time":2.588543061},
{"learn":[0.3312501741],"iteration":186,"passed_time":0.5944607194,"remaining_time":2.584473609},
{"learn":[0.3308014954],"iteration":187,"passed_time":0.5975049605,"remaining_time":2.580712915},
{"learn":[0.330499331],"iteration":188,"passed_time":0.6006106063,"remaining_time":2.57722329},
{"learn":[0.3301802802],"iteration":189,"passed_time":0.6041138721,"remaining_time":2.575432823},
{"learn":[0.3301395203],"iteration":190,"passed_time":0.6064361098,"remaining_time":2.568622057},
{"learn":[0.3298967482],"iteration":191,"passed_time":0.6093532343,"remaining_time":2.564361528},
{"learn":[0.329601252],"iteration":192,"passed_time":0.6124678064,"remaining_time":2.560940517},
{"learn":[0.3293223897],"iteration":193,"passed_time":0.6153997336,"remaining_time":2.556763842},
{"learn":[0.3290227731],"iteration":194,"passed_time":0.6189915339,"remaining_time":2.555324025},
{"learn":[0.3287050466],"iteration":195,"passed_time":0.6218879788,"remaining_time":2.551009872},
{"learn":[0.3285051779],"iteration":196,"passed_time":0.6247095145,"remaining_time":2.546404772},
{"learn":[0.3282837288],"iteration":197,"passed_time":0.6278042013,"remaining_time":2.542924088},
{"learn":[0.3278691778],"iteration":198,"passed_time":0.6309563481,"remaining_time":2.539678567},
{"learn":[0.327508467],"iteration":199,"passed_time":0.6346105705,"remaining_time":2.538442282},
{"learn":[0.3271396564],"iteration":200,"passed_time":0.6375561029,"remaining_time":2.534364807},
{"learn":[0.3267051751],"iteration":201,"passed_time":0.6405385164,"remaining_time":2.530444238},
{"learn":[0.32646175],"iteration":202,"passed_time":0.6434412004,"remaining_time":2.526219885},
{"learn":[0.3260478616],"iteration":203,"passed_time":0.6465344076,"remaining_time":2.522751904},
{"learn":[0.3257716219],"iteration":204,"passed_time":0.6496596358,"remaining_time":2.519411758},
{"learn":[0.3255185868],"iteration":205,"passed_time":0.6530090088,"remaining_time":2.516937636},
{"learn":[0.3251407188],"iteration":206,"passed_time":0.6560946382,"remaining_time":2.513444677},
{"learn":[0.3249333087],"iteration":207,"passed_time":0.6590981344,"remaining_time":2.509642896},
{"learn":[0.324513445],"iteration":208,"passed_time":0.6621671799,"remaining_time":2.506096839},
{"learn":[0.3242204206],"iteration":209,"passed_time":0.6654989174,"remaining_time":2.503543546},
{"learn":[0.3238249923],"iteration":210,"passed_time":0.66869918,"remaining_time":2.500491246},
{"learn":[0.3235570416],"iteration":211,"passed_time":0.6717883623,"remaining_time":2.497024667},
{"learn":[0.3232499673],"iteration":212,"passed_time":0.6748967852,"remaining_time":2.493632723},
{"learn":[0.3230978361],"iteration":213,"passed_time":0.6777600623,"remaining_time":2.489343033},
{"learn":[0.322791256],"iteration":214,"passed_time":0.6810620032,"remaining_time":2.486668244},
{"learn":[0.3226050284],"iteration":215,"passed_time":0.6843027292,"remaining_time":2.483765461},
{"learn":[0.3223600901],"iteration":216,"passed_time":0.6875482912,"remaining_time":2.480877014},
{"learn":[0.3221543055],"iteration":217,"passed_time":0.6906374031,"remaining_time":2.477424079},
{"learn":[0.3219515159],"iteration":218,"passed_time":0.6935886419,"remaining_time":2.473482782},
{"learn":[0.3216626898],"iteration":219,"passed_time":0.6966951924,"remaining_time":2.470101137},
{"learn":[0.3213794942],"iteration":220,"passed_time":0.7000903717,"remaining_time":2.467739364},
{"learn":[0.3210736856],"iteration":221,"passed_time":0.7030625604,"remaining_time":2.46388591},
{"learn":[0.3208285886],"iteration":222,"passed_time":0.7059642381,"remaining_time":2.459794677},
{"learn":[0.3204584585],"iteration":223,"passed_time":0.7090786995,"remaining_time":2.456451209},
{"learn":[0.3202523334],"iteration":224,"passed_time":0.7119774488,"remaining_time":2.452366768},
{"learn":[0.3200402169],"iteration":225,"passed_time":0.7155696121,"remaining_time":2.45066761},
{"learn":[0.3197071688],"iteration":226,"passed_time":0.7193513524,"remaining_time":2.449597336},
{"learn":[0.3194084467],"iteration":227,"passed_time":0.7229204512,"remaining_time":2.447783282},
{"learn":[0.3192817835],"iteration":228,"passed_time":0.7259182718,"remaining_time":2.444030513},
{"learn":[0.3188771995],"iteration":229,"passed_time":0.7292340789,"remaining_time":2.441348873},
{"learn":[0.3185861397],"iteration":230,"passed_time":0.7328686119,"remaining_time":2.439722782},
{"learn":[0.3184023896],"iteration":231,"passed_time":0.7357132322,"remaining_time":2.435464493},
{"learn":[0.3181853317],"iteration":232,"passed_time":0.7385863812,"remaining_time":2.43131225},
{"learn":[0.3178549545],"iteration":233,"passed_time":0.7417318921,"remaining_time":2.428062518},
{"learn":[0.3175937338],"iteration":234,"passed_time":0.7447494601,"remaining_time":2.424397179},
{"learn":[0.3173557444],"iteration":235,"passed_time":0.7483161035,"remaining_time":2.422514844},
{"learn":[0.3170503125],"iteration":236,"passed_time":0.7513455322,"remaining_time":2.418888781},
{"learn":[0.3167111155],"iteration":237,"passed_time":0.7543786124,"remaining_time":2.415279423},
{"learn":[0.3164141532],"iteration":238,"passed_time":0.7576112937,"remaining_time":2.412310437},
{"learn":[0.3161821688],"iteration":239,"passed_time":0.7606237856,"remaining_time":2.408641988},
{"learn":[0.315926173],"iteration":240,"passed_time":0.7639834933,"remaining_time":2.406072496},
{"learn":[0.315692015],"iteration":241,"passed_time":0.7670953373,"remaining_time":2.402720106},
{"learn":[0.31554362],"iteration":242,"passed_time":0.7699454718,"remaining_time":2.398554412},
{"learn":[0.3152091167],"iteration":243,"passed_time":0.7729332193,"remaining_time":2.394825876},
{"learn":[0.314937474],"iteration":244,"passed_time":0.7757589714,"remaining_time":2.390604177},
{"learn":[0.3147941456],"iteration":245,"passed_time":0.7793825106,"remaining_time":2.388839077},
{"learn":[0.3146087754],"iteration":246,"passed_time":0.7825504463,"remaining_time":2.385669984},
{"learn":[0.3142818038],"iteration":247,"passed_time":0.7857504931,"remaining_time":2.382598269},
{"learn":[0.3140395501],"iteration":248,"passed_time":0.7886730718,"remaining_time":2.378688662},
{"learn":[0.3137784013],"iteration":249,"passed_time":0.7918164838,"remaining_time":2.375449451},
{"learn":[0.3135726736],"iteration":250,"passed_time":0.7952199349,"remaining_time":2.372986977},
{"learn":[0.3131876267],"iteration":251,"passed_time":0.7981756317,"remaining_time":2.369187986},
{"learn":[0.312853022],"iteration":252,"passed_time":0.8010965801,"remaining_time":2.365293065},
{"learn":[0.3126645637],"iteration":253,"passed_time":0.8040698258,"remaining_time":2.36155941},
{"learn":[0.3125295829],"iteration":254,"passed_time":0.8073671575,"remaining_time":2.358778558},
{"learn":[0.3121907043],"iteration":255,"passed_time":0.8108522752,"remaining_time":2.356539425},
{"learn":[0.3120226993],"iteration":256,"passed_time":0.8144449211,"remaining_time":2.354601465},
{"learn":[0.3118262897],"iteration":257,"passed_time":0.8175546421,"remaining_time":2.3512618},
{"learn":[0.3116076001],"iteration":258,"passed_time":0.8204814174,"remaining_time":2.347400503},
{"learn":[0.3113291295],"iteration":259,"passed_time":0.8234132333,"remaining_time":2.343560741},
{"learn":[0.3111317026],"iteration":260,"passed_time":0.8269115141,"remaining_time":2.341331835},
{"learn":[0.3109498425],"iteration":261,"passed_time":0.8298349826,"remaining_time":2.337474111},
{"learn":[0.3106502238],"iteration":262,"passed_time":0.8327186934,"remaining_time":2.33351208},
{"learn":[0.310465652],"iteration":263,"passed_time":0.8356667115,"remaining_time":2.329737499},
{"learn":[0.3101850812],"iteration":264,"passed_time":0.8386085809,"remaining_time":2.325952102},
{"learn":[0.3099300714],"iteration":265,"passed_time":0.8418561052,"remaining_time":2.323016471},
{"learn":[0.3096890082],"iteration":266,"passed_time":0.8453467569,"remaining_time":2.320745966},
{"learn":[0.3095629409],"iteration":267,"passed_time":0.8482996354,"remaining_time":2.316997512},
{"learn":[0.3093738892],"iteration":268,"passed_time":0.8512004886,"remaining_time":2.313113595},
{"learn":[0.3091570437],"iteration":269,"passed_time":0.8543898787,"remaining_time":2.310017079},
{"learn":[0.3090934544],"iteration":270,"passed_time":0.8568471121,"remaining_time":2.30495035},
{"learn":[0.308947615],"iteration":271,"passed_time":0.8600780116,"remaining_time":2.301973502},
{"learn":[0.3087968557],"iteration":272,"passed_time":0.8630976583,"remaining_time":2.298432226},
{"learn":[0.3085343144],"iteration":273,"passed_time":0.8659745508,"remaining_time":2.29451651},
{"learn":[0.3084005135],"iteration":274,"passed_time":0.8692356702,"remaining_time":2.291621312},
{"learn":[0.3082105439],"iteration":275,"passed_time":0.8722543113,"remaining_time":2.288087396},
{"learn":[0.307952378],"iteration":276,"passed_time":0.875469714,"remaining_time":2.28507077},
{"learn":[0.307609351],"iteration":277,"passed_time":0.8784568467,"remaining_time":2.281459868},
{"learn":[0.3073565298],"iteration":278,"passed_time":0.8815544116,"remaining_time":2.27813882},
{"learn":[0.3069527595],"iteration":279,"passed_time":0.8846772347,"remaining_time":2.274884318},
{"learn":[0.3068188125],"iteration":280,"passed_time":0.8876177859,"remaining_time":2.27116437},
{"learn":[0.3067000651],"iteration":281,"passed_time":0.8904408511,"remaining_time":2.26715082},
{"learn":[0.3064983321],"iteration":282,"passed_time":0.8935862252,"remaining_time":2.263962274},
{"learn":[0.3061521459],"iteration":283,"passed_time":0.8965441251,"remaining_time":2.260301386},
{"learn":[0.3059887721],"iteration":284,"passed_time":0.8994598414,"remaining_time":2.256539602},
{"learn":[0.3058472905],"iteration":285,"passed_time":0.9024567658,"remaining_time":2.252986471},
{"learn":[0.3055241328],"iteration":286,"passed_time":0.9054423592,"remaining_time":2.249409067},
{"learn":[0.3053597296],"iteration":287,"passed_time":0.9090170926,"remaining_time":2.247292257},
{"learn":[0.3050404277],"iteration":288,"passed_time":0.9122850549,"remaining_time":2.244410637},
{"learn":[0.3047827083],"iteration":289,"passed_time":0.9153821871,"remaining_time":2.241108113},
{"learn":[0.3045607403],"iteration":290,"passed_time":0.9182654393,"remaining_time":2.237285899},
{"learn":[0.3043104583],"iteration":291,"passed_time":0.9213204476,"remaining_time":2.233886565},
{"learn":[0.3040499059],"iteration":292,"passed_time":0.9249285608,"remaining_time":2.231824206},
{"learn":[0.3037916028],"iteration":293,"passed_time":0.9282340489,"remaining_time":2.229024621},
{"learn":[0.3036285962],"iteration":294,"passed_time":0.9311769542,"remaining_time":2.225355094},
{"learn":[0.3033893968],"iteration":295,"passed_time":0.9339819663,"remaining_time":2.221362514},
{"learn":[0.3030936057],"iteration":296,"passed_time":0.9368124983,"remaining_time":2.217438338},
{"learn":[0.3029191664],"iteration":297,"passed_time":0.9401173215,"remaining_time":2.214638791},
{"learn":[0.302674363],"iteration":298,"passed_time":0.9430922381,"remaining_time":2.211062404},
{"learn":[0.3025174881],"iteration":299,"passed_time":0.9459766275,"remaining_time":2.207278797},
{"learn":[0.3022147447],"iteration":300,"passed_time":0.9488294491,"remaining_time":2.203427857},
{"learn":[0.3020576389],"iteration":301,"passed_time":0.9516635032,"remaining_time":2.19954015},
{"learn":[0.3018990858],"iteration":302,"passed_time":0.9548154695,"remaining_time":2.1963907},
{"learn":[0.3015609139],"iteration":303,"passed_time":0.9585536468,"remaining_time":2.194583349},
{"learn":[0.3011670773],"iteration":304,"passed_time":0.9622450015,"remaining_time":2.192656643},
{"learn":[0.3008838942],"iteration":305,"passed_time":0.9652911543,"remaining_time":2.189255102},
{"learn":[0.3007914177],"iteration":306,"passed_time":0.9681387532,"remaining_time":2.185407674},
{"learn":[0.3006383452],"iteration":307,"passed_time":0.971862048,"remaining_time":2.183534212},
{"learn":[0.3003194113],"iteration":308,"passed_time":0.9749542395,"remaining_time":2.180237474},
{"learn":[0.3002210837],"iteration":309,"passed_time":0.9778800584,"remaining_time":2.176571743},
{"learn":[0.2999709042],"iteration":310,"passed_time":0.9807199591,"remaining_time":2.172720424},
{"learn":[0.2998648136],"iteration":311,"passed_time":0.9836771543,"remaining_time":2.169134238},
{"learn":[0.2996675513],"iteration":312,"passed_time":0.9876513213,"remaining_time":2.16778421},
{"learn":[0.299442437],"iteration":313,"passed_time":0.9906722052,"remaining_time":2.164334818},
{"learn":[0.2993163343],"iteration":314,"passed_time":0.9935515536,"remaining_time":2.160580363},
{"learn":[0.2991273024],"iteration":315,"passed_time":0.9965843521,"remaining_time":2.157163598},
{"learn":[0.2989796458],"iteration":316,"passed_time":0.9995886326,"remaining_time":2.153687811},
{"learn":[0.2988249326],"iteration":317,"passed_time":1.002776916,"remaining_time":2.150609612},
{"learn":[0.2985484836],"iteration":318,"passed_time":1.006096864,"remaining_time":2.1478118},
{"learn":[0.2983782987],"iteration":319,"passed_time":1.008869251,"remaining_time":2.143847159},
{"learn":[0.2982721587],"iteration":320,"passed_time":1.012018822,"remaining_time":2.140687789},
{"learn":[0.2980293347],"iteration":321,"passed_time":1.015066253,"remaining_time":2.137313414},
{"learn":[0.2977840382],"iteration":322,"passed_time":1.018170389,"remaining_time":2.134059917},
{"learn":[0.2976171296],"iteration":323,"passed_time":1.0218037,"remaining_time":2.131911423},
{"learn":[0.2973524294],"iteration":324,"passed_time":1.025035123,"remaining_time":2.128919102},
{"learn":[0.2970600398],"iteration":325,"passed_time":1.028137378,"remaining_time":2.125658261},
{"learn":[0.2969720101],"iteration":326,"passed_time":1.0309872,"remaining_time":2.121878856},
{"learn":[0.2968736161],"iteration":327,"passed_time":1.034355281,"remaining_time":2.119166916},
{"learn":[0.2967044548],"iteration":328,"passed_time":1.037573289,"remaining_time":2.116144915},
{"learn":[0.2964902041],"iteration":329,"passed_time":1.040634467,"remaining_time":2.112803312},
{"learn":[0.2962649731],"iteration":330,"passed_time":1.043596764,"remaining_time":2.10926355},
{"learn":[0.296043775],"iteration":331,"passed_time":1.046610564,"remaining_time":2.105830893},
{"learn":[0.2957873914],"iteration":332,"passed_time":1.049538516,"remaining_time":2.1022288},
{"learn":[0.2955427792],"iteration":333,"passed_time":1.053085033,"remaining_time":2.099864169},
{"learn":[0.2953547151],"iteration":334,"passed_time":1.056091538,"remaining_time":2.096420515},
{"learn":[0.2951725824],"iteration":335,"passed_time":1.058969044,"remaining_time":2.09272454},
{"learn":[0.2950352477],"iteration":336,"passed_time":1.061971534,"remaining_time":2.089279309},
{"learn":[0.2948312349],"iteration":337,"passed_time":1.065229594,"remaining_time":2.086337251},
{"learn":[0.2947271457],"iteration":338,"passed_time":1.069269311,"remaining_time":2.084917446},
{"learn":[0.2945917043],"iteration":339,"passed_time":1.072186909,"remaining_time":2.081303999},
{"learn":[0.2943949926],"iteration":340,"passed_time":1.075180451,"remaining_time":2.0778414},
{"learn":[0.2942379029],"iteration":341,"passed_time":1.078071744,"remaining_time":2.074184817},
{"learn":[0.2940895534],"iteration":342,"passed_time":1.081160997,"remaining_time":2.07091188},
{"learn":[0.2938326321],"iteration":343,"passed_time":1.084469412,"remaining_time":2.068057949},
{"learn":[0.2936600947],"iteration":344,"passed_time":1.087568326,"remaining_time":2.064803634},
{"learn":[0.2935113842],"iteration":345,"passed_time":1.09044699,"remaining_time":2.061133906},
{"learn":[0.2933469957],"iteration":346,"passed_time":1.093547976,"remaining_time":2.057887114},
{"learn":[0.2931301622],"iteration":347,"passed_time":1.096657123,"remaining_time":2.054656449},
{"learn":[0.2929187369],"iteration":348,"passed_time":1.100218916,"remaining_time":2.052270815},
{"learn":[0.2927767058],"iteration":349,"passed_time":1.103262966,"remaining_time":2.048916937},
{"learn":[0.2926136867],"iteration":350,"passed_time":1.106201445,"remaining_time":2.045369623},
{"learn":[0.2923921236],"iteration":351,"passed_time":1.109207656,"remaining_time":2.041950458},
{"learn":[0.2922308555],"iteration":352,"passed_time":1.112539066,"remaining_time":2.039129677},
{"learn":[0.2920614459],"iteration":353,"passed_time":1.116177933,"remaining_time":2.036867075},
{"learn":[0.2918252672],"iteration":354,"passed_time":1.119897031,"remaining_time":2.034742493},
{"learn":[0.291640263],"iteration":355,"passed_time":1.123040514,"remaining_time":2.031567671},
{"learn":[0.2915104768],"iteration":356,"passed_time":1.125845033,"remaining_time":2.02778251},
{"learn":[0.29138199],"iteration":357,"passed_time":1.128988798,"remaining_time":2.024611196},
{"learn":[0.2912341676],"iteration":358,"passed_time":1.132408077,"remaining_time":2.021931971},
{"learn":[0.2910153885],"iteration":359,"passed_time":1.135583661,"remaining_time":2.018815397},
{"learn":[0.2907899622],"iteration":360,"passed_time":1.13843929,"remaining_time":2.015132151},
{"learn":[0.2906206532],"iteration":361,"passed_time":1.141495697,"remaining_time":2.011807334},
{"learn":[0.2905015249],"iteration":362,"passed_time":1.144528064,"remaining_time":2.008441809},
{"learn":[0.2903638062],"iteration":363,"passed_time":1.14782697,"remaining_time":2.005543826},
{"learn":[0.290268495],"iteration":364,"passed_time":1.150786732,"remaining_time":2.00205363},
{"learn":[0.2900599488],"iteration":365,"passed_time":1.15370925,"remaining_time":1.998501815},
{"learn":[0.2899433578],"iteration":366,"passed_time":1.157157723,"remaining_time":1.995860595},
{"learn":[0.2897574408],"iteration":367,"passed_time":1.16009921,"remaining_time":1.992344295},
{"learn":[0.2896443205],"iteration":368,"passed_time":1.163728586,"remaining_time":1.99000742},
{"learn":[0.2894225611],"iteration":369,"passed_time":1.166615834,"remaining_time":1.986399933},
{"learn":[0.2892778214],"iteration":370,"passed_time":1.169621056,"remaining_time":1.982996345},
{"learn":[0.2890190465],"iteration":371,"passed_time":1.172705925,"remaining_time":1.979729358},
{"learn":[0.2889207368],"iteration":372,"passed_time":1.175588323,"remaining_time":1.976122998},
{"learn":[0.2887125727],"iteration":373,"passed_time":1.178885477,"remaining_time":1.973214729},
{"learn":[0.2886130984],"iteration":374,"passed_time":1.182219856,"remaining_time":1.970366426},
{"learn":[0.2884657459],"iteration":375,"passed_time":1.185221435,"remaining_time":1.966963232},
{"learn":[0.2882526097],"iteration":376,"passed_time":1.188035393,"remaining_time":1.963252122},
{"learn":[0.2880438675],"iteration":377,"passed_time":1.191127187,"remaining_time":1.960002937},
{"learn":[0.287809462],"iteration":378,"passed_time":1.19401216,"remaining_time":1.956415703},
{"learn":[0.2875360409],"iteration":379,"passed_time":1.19740512,"remaining_time":1.953660985},
{"learn":[0.2873722022],"iteration":380,"passed_time":1.200435947,"remaining_time":1.95031457},
{"learn":[0.2871095056],"iteration":381,"passed_time":1.203291365,"remaining_time":1.94668603},
{"learn":[0.286923934],"iteration":382,"passed_time":1.20625963,"remaining_time":1.94324332},
{"learn":[0.286607895],"iteration":383,"passed_time":1.20909947,"remaining_time":1.939597067},
{"learn":[0.286392444],"iteration":384,"passed_time":1.212547702,"remaining_time":1.936926848},
{"learn":[0.2861914448],"iteration":385,"passed_time":1.215576888,"remaining_time":1.933586035},
{"learn":[0.2860371025],"iteration":386,"passed_time":1.21856559,"remaining_time":1.930182705},
{"learn":[0.2858478255],"iteration":387,"passed_time":1.221441909,"remaining_time":1.926604249},
{"learn":[0.2855479622],"iteration":388,"passed_time":1.224359014,"remaining_time":1.923093463},
{"learn":[0.285301629],"iteration":389,"passed_time":1.228077096,"remaining_time":1.920838534},
{"learn":[0.2850475695],"iteration":390,"passed_time":1.231497594,"remaining_time":1.91811262},
{"learn":[0.2848227711],"iteration":391,"passed_time":1.235449119,"remaining_time":1.916206796},
{"learn":[0.2846800763],"iteration":392,"passed_time":1.23841694,"remaining_time":1.912771203},
{"learn":[0.2845254793],"iteration":393,"passed_time":1.241590844,"remaining_time":1.909654953},
{"learn":[0.284268084],"iteration":394,"passed_time":1.245229428,"remaining_time":1.907250137},
{"learn":[0.2840468957],"iteration":395,"passed_time":1.2488278,"remaining_time":1.904777755},
{"learn":[0.2838192024],"iteration":396,"passed_time":1.251821362,"remaining_time":1.901381061},
{"learn":[0.283614347],"iteration":397,"passed_time":1.254877719,"remaining_time":1.898081374},
{"learn":[0.2833661842],"iteration":398,"passed_time":1.257689856,"remaining_time":1.894415046},
{"learn":[0.2831066768],"iteration":399,"passed_time":1.261615236,"remaining_time":1.892422855},
{"learn":[0.282939915],"iteration":400,"passed_time":1.26502218,"remaining_time":1.889646598},
{"learn":[0.2827455918],"iteration":401,"passed_time":1.267995114,"remaining_time":1.886221587},
{"learn":[0.2825842736],"iteration":402,"passed_time":1.270932908,"remaining_time":1.882746764},
{"learn":[0.2823809219],"iteration":403,"passed_time":1.273842747,"remaining_time":1.879233359},
{"learn":[0.2821681903],"iteration":404,"passed_time":1.277577946,"remaining_time":1.876935501},
{"learn":[0.2820279988],"iteration":405,"passed_time":1.281221431,"remaining_time":1.874496379},
{"learn":[0.2818383764],"iteration":406,"passed_time":1.284189796,"remaining_time":1.871067688},
{"learn":[0.2816732449],"iteration":407,"passed_time":1.287047297,"remaining_time":1.867480391},
{"learn":[0.2814247815],"iteration":408,"passed_time":1.290101269,"remaining_time":1.864180562},
{"learn":[0.2812786835],"iteration":409,"passed_time":1.293597662,"remaining_time":1.861518587},
{"learn":[0.2811596905],"iteration":410,"passed_time":1.297253726,"remaining_time":1.859081373},
{"learn":[0.2810383861],"iteration":411,"passed_time":1.300267234,"remaining_time":1.855721198},
{"learn":[0.2808589067],"iteration":412,"passed_time":1.303384337,"remaining_time":1.852509941},
{"learn":[0.2806786167],"iteration":413,"passed_time":1.306320053,"remaining_time":1.849042393},
{"learn":[0.2805544868],"iteration":414,"passed_time":1.310070769,"remaining_time":1.846726265},
{"learn":[0.2803703408],"iteration":415,"passed_time":1.313851544,"remaining_time":1.844445437},
{"learn":[0.2802153249],"iteration":416,"passed_time":1.317017307,"remaining_time":1.841297578},
{"learn":[0.2800179146],"iteration":417,"passed_time":1.320008656,"remaining_time":1.837906788},
{"learn":[0.2799177409],"iteration":418,"passed_time":1.323761606,"remaining_time":1.835573969},
{"learn":[0.2796263421],"iteration":419,"passed_time":1.327251479,"remaining_time":1.832871089},
{"learn":[0.2794671588],"iteration":420,"passed_time":1.330712561,"remaining_time":1.830124877},
{"learn":[0.2793183297],"iteration":421,"passed_time":1.333824616,"remaining_time":1.826897223},
{"learn":[0.2791314446],"iteration":422,"passed_time":1.336850905,"remaining_time":1.823553125},
{"learn":[0.2789860404],"iteration":423,"passed_time":1.340298121,"remaining_time":1.820782353},
{"learn":[0.2787872501],"iteration":424,"passed_time":1.343743614,"remaining_time":1.818006067},
{"learn":[0.2785338295],"iteration":425,"passed_time":1.347236586,"remaining_time":1.815290612},
{"learn":[0.2784031446],"iteration":426,"passed_time":1.350341648,"remaining_time":1.81205097},
{"learn":[0.2781567914],"iteration":427,"passed_time":1.353376611,"remaining_time":1.808718274},
{"learn":[0.2779989583],"iteration":428,"passed_time":1.357180058,"remaining_time":1.80640982},
{"learn":[0.2778217162],"iteration":429,"passed_time":1.360327637,"remaining_time":1.803225007},
{"learn":[0.2775798299],"iteration":430,"passed_time":1.363336636,"remaining_time":1.799857415},
{"learn":[0.2774427489],"iteration":431,"passed_time":1.366100169,"remaining_time":1.79616874},
{"learn":[0.2772649827],"iteration":432,"passed_time":1.369090602,"remaining_time":1.792781458},
{"learn":[0.2770849923],"iteration":433,"passed_time":1.372913883,"remaining_time":1.790482161},
{"learn":[0.2769630377],"iteration":434,"passed_time":1.376684846,"remaining_time":1.788107904},
{"learn":[0.2768206317],"iteration":435,"passed_time":1.379988634,"remaining_time":1.785122912},
{"learn":[0.276607882],"iteration":436,"passed_time":1.383007153,"remaining_time":1.781768941},
{"learn":[0.2763352438],"iteration":437,"passed_time":1.386039419,"remaining_time":1.77843414},
{"learn":[0.2760662589],"iteration":438,"passed_time":1.389850896,"remaining_time":1.776096476},
{"learn":[0.275821915],"iteration":439,"passed_time":1.393322544,"remaining_time":1.773319602},
{"learn":[0.275658578],"iteration":440,"passed_time":1.396336646,"remaining_time":1.769959604},
{"learn":[0.2754321301],"iteration":441,"passed_time":1.399321968,"remaining_time":1.766564838},
{"learn":[0.2752072153],"iteration":442,"passed_time":1.402276618,"remaining_time":1.763133355},
{"learn":[0.2750617118],"iteration":443,"passed_time":1.405901546,"remaining_time":1.760543378},
{"learn":[0.2749586226],"iteration":444,"passed_time":1.409076415,"remaining_time":1.757387439},
{"learn":[0.2747692043],"iteration":445,"passed_time":1.412021777,"remaining_time":1.753946333},
{"learn":[0.2745403189],"iteration":446,"passed_time":1.414888334,"remaining_time":1.750409953},
{"learn":[0.274355573],"iteration":447,"passed_time":1.417750424,"remaining_time":1.746871058},
{"learn":[0.2741866201],"iteration":448,"passed_time":1.421417265,"remaining_time":1.744322746},
{"learn":[0.27401568],"iteration":449,"passed_time":1.424921699,"remaining_time":1.741570966},
{"learn":[0.2738522132],"iteration":450,"passed_time":1.427945341,"remaining_time":1.738230581},
{"learn":[0.2736624655],"iteration":451,"passed_time":1.430752818,"remaining_time":1.734629523},
{"learn":[0.273471795],"iteration":452,"passed_time":1.433661077,"remaining_time":1.731153662},
{"learn":[0.2732603007],"iteration":453,"passed_time":1.436979063,"remaining_time":1.728173058},
{"learn":[0.2730492535],"iteration":454,"passed_time":1.440280787,"remaining_time":1.725171492},
{"learn":[0.2728553335],"iteration":455,"passed_time":1.443365763,"remaining_time":1.721910033},
{"learn":[0.2727396114],"iteration":456,"passed_time":1.446384614,"remaining_time":1.718570778},
{"learn":[0.2724688363],"iteration":457,"passed_time":1.449413187,"remaining_time":1.715244426},
{"learn":[0.2722810594],"iteration":458,"passed_time":1.452858048,"remaining_time":1.71241003},
{"learn":[0.2719799109],"iteration":459,"passed_time":1.456119006,"remaining_time":1.709357094},
{"learn":[0.271766833],"iteration":460,"passed_time":1.459645769,"remaining_time":1.706614034},
{"learn":[0.2715616448],"iteration":461,"passed_time":1.462657326,"remaining_time":1.703267622},
{"learn":[0.2713866736],"iteration":462,"passed_time":1.465521318,"remaining_time":1.699751507},
{"learn":[0.2711972242],"iteration":463,"passed_time":1.469084645,"remaining_time":1.697046056},
{"learn":[0.2709764959],"iteration":464,"passed_time":1.472246417,"remaining_time":1.69387491},
{"learn":[0.2708020422],"iteration":465,"passed_time":1.475247095,"remaining_time":1.690519203},
{"learn":[0.2706266392],"iteration":466,"passed_time":1.478002657,"remaining_time":1.68688526},
{"learn":[0.2704641146],"iteration":467,"passed_time":1.480965871,"remaining_time":1.683491118},
{"learn":[0.2702374849],"iteration":468,"passed_time":1.484142994,"remaining_time":1.680341002},
{"learn":[0.2700352105],"iteration":469,"passed_time":1.487362422,"remaining_time":1.677238476},
{"learn":[0.2698322932],"iteration":470,"passed_time":1.490418719,"remaining_time":1.673952234},
{"learn":[0.269586994],"iteration":471,"passed_time":1.493400478,"remaining_time":1.670583586},
{"learn":[0.2694290431],"iteration":472,"passed_time":1.496314614,"remaining_time":1.667141229},
{"learn":[0.2692162502],"iteration":473,"passed_time":1.500054875,"remaining_time":1.664617857},
{"learn":[0.2690383283],"iteration":474,"passed_time":1.504341026,"remaining_time":1.662692713},
{"learn":[0.2689322784],"iteration":475,"passed_time":1.50759181,"remaining_time":1.659617875},
{"learn":[0.2687903999],"iteration":476,"passed_time":1.510601595,"remaining_time":1.656278059},
{"learn":[0.2685649454],"iteration":477,"passed_time":1.514107207,"remaining_time":1.653481092},
{"learn":[0.2683777518],"iteration":478,"passed_time":1.517775587,"remaining_time":1.650858206},
{"learn":[0.2681190114],"iteration":479,"passed_time":1.52093984,"remaining_time":1.647684826},
{"learn":[0.2678854581],"iteration":480,"passed_time":1.524021364,"remaining_time":1.64442222},
{"learn":[0.2677105049],"iteration":481,"passed_time":1.526969302,"remaining_time":1.641016801},
{"learn":[0.2675424951],"iteration":482,"passed_time":1.530391852,"remaining_time":1.6381213},
{"learn":[0.2673421083],"iteration":483,"passed_time":1.53364314,"remaining_time":1.635041034},
{"learn":[0.2671748367],"iteration":484,"passed_time":1.536491393,"remaining_time":1.631532098},
{"learn":[0.2669634804],"iteration":485,"passed_time":1.539505893,"remaining_time":1.628201706},
{"learn":[0.2667260542],"iteration":486,"passed_time":1.542513862,"remaining_time":1.624865731},
{"learn":[0.2666050287],"iteration":487,"passed_time":1.545643366,"remaining_time":1.621658614},
{"learn":[0.2664429171],"iteration":488,"passed_time":1.549233688,"remaining_time":1.618933363},
{"learn":[0.2662735959],"iteration":489,"passed_time":1.552116931,"remaining_time":1.615468642},
{"learn":[0.266078711],"iteration":490,"passed_time":1.555088425,"remaining_time":1.612097777},
{"learn":[0.2658260244],"iteration":491,"passed_time":1.557961816,"remaining_time":1.608627241},
{"learn":[0.2656672828],"iteration":492,"passed_time":1.560917613,"remaining_time":1.605243874},
{"learn":[0.2654695516],"iteration":493,"passed_time":1.564206647,"remaining_time":1.602203569},
{"learn":[0.2653329311],"iteration":494,"passed_time":1.567433652,"remaining_time":1.599098979},
{"learn":[0.2651885799],"iteration":495,"passed_time":1.570352125,"remaining_time":1.595680385},
{"learn":[0.2649622918],"iteration":496,"passed_time":1.573548887,"remaining_time":1.592545453},
{"learn":[0.2646896206],"iteration":497,"passed_time":1.576717672,"remaining_time":1.589382071},
{"learn":[0.2645008915],"iteration":498,"passed_time":1.580169075,"remaining_time":1.586502418},
{"learn":[0.2643572997],"iteration":499,"passed_time":1.583124196,"remaining_time":1.583124196},
{"learn":[0.264219072],"iteration":500,"passed_time":1.586008909,"remaining_time":1.579677536},
{"learn":[0.2641119752],"iteration":501,"passed_time":1.589019951,"remaining_time":1.576358437},
{"learn":[0.2639824735],"iteration":502,"passed_time":1.59205748,"remaining_time":1.573066735},
{"learn":[0.2638567334],"iteration":503,"passed_time":1.595647389,"remaining_time":1.570319653},
{"learn":[0.2636677857],"iteration":504,"passed_time":1.599322376,"remaining_time":1.567652626},
{"learn":[0.2634938862],"iteration":505,"passed_time":1.602473753,"remaining_time":1.564470423},
{"learn":[0.2633116659],"iteration":506,"passed_time":1.605414525,"remaining_time":1.561083552},
{"learn":[0.2631556273],"iteration":507,"passed_time":1.608703117,"remaining_time":1.558035302},
{"learn":[0.2630044102],"iteration":508,"passed_time":1.612254927,"remaining_time":1.555240018},
{"learn":[0.2628576605],"iteration":509,"passed_time":1.615861239,"remaining_time":1.552494132},
{"learn":[0.2626850573],"iteration":510,"passed_time":1.618900378,"remaining_time":1.549202123},
{"learn":[0.2625739867],"iteration":511,"passed_time":1.621826802,"remaining_time":1.54580367},
{"learn":[0.2623705023],"iteration":512,"passed_time":1.624954596,"remaining_time":1.542598222},
{"learn":[0.2622004099],"iteration":513,"passed_time":1.628213642,"remaining_time":1.539517179},
{"learn":[0.262101702],"iteration":514,"passed_time":1.631121156,"remaining_time":1.536104389},
{"learn":[0.2619320612],"iteration":515,"passed_time":1.634081219,"remaining_time":1.532742849},
{"learn":[0.2616922308],"iteration":516,"passed_time":1.637217427,"remaining_time":1.529547422},
{"learn":[0.261530059],"iteration":517,"passed_time":1.640196418,"remaining_time":1.526205934},
{"learn":[0.2613141657],"iteration":518,"passed_time":1.643915004,"remaining_time":1.523551285},
{"learn":[0.2611368908],"iteration":519,"passed_time":1.646861029,"remaining_time":1.520179411},
{"learn":[0.2609659701],"iteration":520,"passed_time":1.650341201,"remaining_time":1.51730026},
{"learn":[0.2607690957],"iteration":521,"passed_time":1.653192432,"remaining_time":1.513842879},
{"learn":[0.2606215631],"iteration":522,"passed_time":1.656571984,"remaining_time":1.510869668},
{"learn":[0.2604442531],"iteration":523,"passed_time":1.6601965,"remaining_time":1.508117432},
{"learn":[0.2602921909],"iteration":524,"passed_time":1.663247875,"remaining_time":1.504843316},
{"learn":[0.260115843],"iteration":525,"passed_time":1.666276066,"remaining_time":1.501549154},
{"learn":[0.2599196994],"iteration":526,"passed_time":1.669204944,"remaining_time":1.498166866},
{"learn":[0.2598038668],"iteration":527,"passed_time":1.672254035,"remaining_time":1.494893758},
{"learn":[0.2595877285],"iteration":528,"passed_time":1.675891613,"remaining_time":1.492145462},
{"learn":[0.2593976743],"iteration":529,"passed_time":1.678733586,"remaining_time":1.488688275},
{"learn":[0.2592478389],"iteration":530,"passed_time":1.681745223,"remaining_time":1.485383258},
{"learn":[0.2591131861],"iteration":531,"passed_time":1.684617255,"remaining_time":1.481956533},
{"learn":[0.2589255132],"iteration":532,"passed_time":1.687582692,"remaining_time":1.478613728},
{"learn":[0.2588120866],"iteration":533,"passed_time":1.69123307,"remaining_time":1.475870057},
{"learn":[0.2586482459],"iteration":534,"passed_time":1.694849435,"remaining_time":1.473093434},
{"learn":[0.2585130912],"iteration":535,"passed_time":1.698034498,"remaining_time":1.469940312},
{"learn":[0.2583273643],"iteration":536,"passed_time":1.700918354,"remaining_time":1.46652737},
{"learn":[0.2581975991],"iteration":537,"passed_time":1.703690591,"remaining_time":1.463020544},
{"learn":[0.2580491772],"iteration":538,"passed_time":1.707537822,"remaining_time":1.460435874},
{"learn":[0.2578810188],"iteration":539,"passed_time":1.711034739,"remaining_time":1.457548111},
{"learn":[0.2576996604],"iteration":540,"passed_time":1.714054174,"remaining_time":1.454252987},
{"learn":[0.2575470781],"iteration":541,"passed_time":1.716943233,"remaining_time":1.450848709},
{"learn":[0.2574458001],"iteration":542,"passed_time":1.719767495,"remaining_time":1.447391796},
{"learn":[0.2572679968],"iteration":543,"passed_time":1.723194263,"remaining_time":1.44444225},
{"learn":[0.2571269726],"iteration":544,"passed_time":1.726187876,"remaining_time":1.441129328},
{"learn":[0.2569470404],"iteration":545,"passed_time":1.729038846,"remaining_time":1.437698967},
{"learn":[0.2567893985],"iteration":546,"passed_time":1.732270315,"remaining_time":1.434585837},
{"learn":[0.2566810372],"iteration":547,"passed_time":1.735168552,"remaining_time":1.431197418},
{"learn":[0.2565030819],"iteration":548,"passed_time":1.738808951,"remaining_time":1.428420468},
{"learn":[0.2563322101],"iteration":549,"passed_time":1.741747993,"remaining_time":1.42506654},
{"learn":[0.2561135108],"iteration":550,"passed_time":1.744622118,"remaining_time":1.421661218},
{"learn":[0.2558901228],"iteration":551,"passed_time":1.747546106,"remaining_time":1.418298289},
{"learn":[0.255786167],"iteration":552,"passed_time":1.750422807,"remaining_time":1.414898725},
{"learn":[0.2556603167],"iteration":553,"passed_time":1.753553111,"remaining_time":1.411705212},
{"learn":[0.2554761578],"iteration":554,"passed_time":1.756675105,"remaining_time":1.408505264},
{"learn":[0.2553131491],"iteration":555,"passed_time":1.759522653,"remaining_time":1.405086435},
{"learn":[0.2551593091],"iteration":556,"passed_time":1.762448774,"remaining_time":1.401732149},
{"learn":[0.2549982528],"iteration":557,"passed_time":1.765394629,"remaining_time":1.398395028},
{"learn":[0.2548456384],"iteration":558,"passed_time":1.768446119,"remaining_time":1.395142645},
{"learn":[0.2547116432],"iteration":559,"passed_time":1.771729333,"remaining_time":1.392073047},
{"learn":[0.2545451718],"iteration":560,"passed_time":1.774615795,"remaining_time":1.388692218},
{"learn":[0.2543907642],"iteration":561,"passed_time":1.777736269,"remaining_time":1.385495526},
{"learn":[0.2542484635],"iteration":562,"passed_time":1.780674224,"remaining_time":1.382157435},
{"learn":[0.2541221947],"iteration":563,"passed_time":1.783770505,"remaining_time":1.378943157},
{"learn":[0.2539769812],"iteration":564,"passed_time":1.787306411,"remaining_time":1.376067768},
{"learn":[0.2538385376],"iteration":565,"passed_time":1.79015403,"remaining_time":1.372662278},
{"learn":[0.2536651756],"iteration":566,"passed_time":1.79309911,"remaining_time":1.369333183},
{"learn":[0.2535457733],"iteration":567,"passed_time":1.796032335,"remaining_time":1.365996424},
{"learn":[0.2533886502],"iteration":568,"passed_time":1.798960136,"remaining_time":1.362656975},
{"learn":[0.2532280218],"iteration":569,"passed_time":1.802070461,"remaining_time":1.359456663},
{"learn":[0.2530610073],"iteration":570,"passed_time":1.805024134,"remaining_time":1.356138973},
{"learn":[0.2529219922],"iteration":571,"passed_time":1.807939921,"remaining_time":1.352794206},
{"learn":[0.2527791569],"iteration":572,"passed_time":1.810718638,"remaining_time":1.349348793},
{"learn":[0.2526431813],"iteration":573,"passed_time":1.813548144,"remaining_time":1.345943396},
{"learn":[0.2524653906],"iteration":574,"passed_time":1.816562185,"remaining_time":1.342676397},
{"learn":[0.2523053682],"iteration":575,"passed_time":1.819805895,"remaining_time":1.339579339},
{"learn":[0.2521459432],"iteration":576,"passed_time":1.823438905,"remaining_time":1.336767169},
{"learn":[0.2520285254],"iteration":577,"passed_time":1.826324059,"remaining_time":1.333406147},
{"learn":[0.2518175522],"iteration":578,"passed_time":1.829258532,"remaining_time":1.330082629},
{"learn":[0.2516262806],"iteration":579,"passed_time":1.832248685,"remaining_time":1.326800772},
{"learn":[0.2513783277],"iteration":580,"passed_time":1.835606388,"remaining_time":1.323784986},
{"learn":[0.2512041025],"iteration":581,"passed_time":1.838487839,"remaining_time":1.320425974},
{"learn":[0.2510167865],"iteration":582,"passed_time":1.841467325,"remaining_time":1.317138721},
{"learn":[0.2508775584],"iteration":583,"passed_time":1.844417034,"remaining_time":1.313831312},
{"learn":[0.2507719349],"iteration":584,"passed_time":1.847309846,"remaining_time":1.310484763},
{"learn":[0.2506583042],"iteration":585,"passed_time":1.850481867,"remaining_time":1.307337018},
{"learn":[0.2505034181],"iteration":586,"passed_time":1.853524941,"remaining_time":1.304098468},
{"learn":[0.2503648465],"iteration":587,"passed_time":1.856437405,"remaining_time":1.300769066},
{"learn":[0.2501847327],"iteration":588,"passed_time":1.859318705,"remaining_time":1.297419334},
{"learn":[0.2500493689],"iteration":589,"passed_time":1.862323449,"remaining_time":1.294156973},
{"learn":[0.249842711],"iteration":590,"passed_time":1.865349788,"remaining_time":1.290910429},
{"learn":[0.2496023121],"iteration":591,"passed_time":1.868583606,"remaining_time":1.28780762},
{"learn":[0.24947103],"iteration":592,"passed_time":1.871480886,"remaining_time":1.284473391},
{"learn":[0.2491344582],"iteration":593,"passed_time":1.874402267,"remaining_time":1.281157105},
{"learn":[0.2489805439],"iteration":594,"passed_time":1.877463635,"remaining_time":1.277937432},
{"learn":[0.2488208912],"iteration":595,"passed_time":1.880362616,"remaining_time":1.274608216},
{"learn":[0.2486908251],"iteration":596,"passed_time":1.883761207,"remaining_time":1.271617699},
{"learn":[0.2485385388],"iteration":597,"passed_time":1.886603965,"remaining_time":1.268252164},
{"learn":[0.248321013],"iteration":598,"passed_time":1.889411312,"remaining_time":1.264864668},
{"learn":[0.2481530197],"iteration":599,"passed_time":1.892677363,"remaining_time":1.261784909},
{"learn":[0.2479320542],"iteration":600,"passed_time":1.895704778,"remaining_time":1.258546101},
{"learn":[0.2477437689],"iteration":601,"passed_time":1.899740611,"remaining_time":1.25597469},
{"learn":[0.247603559],"iteration":602,"passed_time":1.902600406,"remaining_time":1.252624148},
{"learn":[0.2474686447],"iteration":603,"passed_time":1.905580325,"remaining_time":1.249353988},
{"learn":[0.2473775705],"iteration":604,"passed_time":1.908488906,"remaining_time":1.246038211},
{"learn":[0.2472149726],"iteration":605,"passed_time":1.911396571,"remaining_time":1.242723183},
{"learn":[0.2470381055],"iteration":606,"passed_time":1.914725957,"remaining_time":1.239682539},
{"learn":[0.246932942],"iteration":607,"passed_time":1.918213073,"remaining_time":1.236742639},
{"learn":[0.2468234103],"iteration":608,"passed_time":1.921422146,"remaining_time":1.233622429},
{"learn":[0.2466811924],"iteration":609,"passed_time":1.924350752,"remaining_time":1.230322612},
{"learn":[0.2465060263],"iteration":610,"passed_time":1.927296738,"remaining_time":1.227035075},
{"learn":[0.2462980958],"iteration":611,"passed_time":1.930622855,"remaining_time":1.223989653},
{"learn":[0.2461727686],"iteration":612,"passed_time":1.933589832,"remaining_time":1.220716583},
{"learn":[0.2460045143],"iteration":613,"passed_time":1.936526992,"remaining_time":1.217425764},
{"learn":[0.2458573816],"iteration":614,"passed_time":1.939450638,"remaining_time":1.214127635},
{"learn":[0.2456673648],"iteration":615,"passed_time":1.942543382,"remaining_time":1.210936134},
{"learn":[0.2455272941],"iteration":616,"passed_time":1.945696927,"remaining_time":1.207782695},
{"learn":[0.2453574735],"iteration":617,"passed_time":1.949072977,"remaining_time":1.204766791},
{"learn":[0.2451810885],"iteration":618,"passed_time":1.952105061,"remaining_time":1.20153801},
{"learn":[0.2450655852],"iteration":619,"passed_time":1.955010362,"remaining_time":1.198232157},
{"learn":[0.2449361472],"iteration":620,"passed_time":1.957971633,"remaining_time":1.194961753},
{"learn":[0.2447900661],"iteration":621,"passed_time":1.960920104,"remaining_time":1.191684565},
{"learn":[0.2445196034],"iteration":622,"passed_time":1.964320646,"remaining_time":1.188681996},
{"learn":[0.2443480739],"iteration":623,"passed_time":1.967374568,"remaining_time":1.185469291},
{"learn":[0.2442523526],"iteration":624,"passed_time":1.97037113,"remaining_time":1.182222678},
{"learn":[0.2441177463],"iteration":625,"passed_time":1.973448167,"remaining_time":1.179024943},
{"learn":[0.2440014028],"iteration":626,"passed_time":1.976366217,"remaining_time":1.175733013},
{"learn":[0.2439006805],"iteration":627,"passed_time":1.979611477,"remaining_time":1.172636098},
{"learn":[0.2438044713],"iteration":628,"passed_time":1.982541079,"remaining_time":1.169352528},
{"learn":[0.2436994908],"iteration":629,"passed_time":1.985357644,"remaining_time":1.166003696},
{"learn":[0.2435385446],"iteration":630,"passed_time":1.988194898,"remaining_time":1.162668649},
{"learn":[0.2433992246],"iteration":631,"passed_time":1.991153432,"remaining_time":1.159405796},
{"learn":[0.2432836503],"iteration":632,"passed_time":1.994303627,"remaining_time":1.156255025},
{"learn":[0.2431105559],"iteration":633,"passed_time":1.997837032,"remaining_time":1.153325479},
{"learn":[0.2429918782],"iteration":634,"passed_time":2.000789166,"remaining_time":1.150059914},
{"learn":[0.2428370733],"iteration":635,"passed_time":2.003726557,"remaining_time":1.146786898},
{"learn":[0.2426090679],"iteration":636,"passed_time":2.006689781,"remaining_time":1.143529655},
{"learn":[0.2424583596],"iteration":637,"passed_time":2.009657954,"remaining_time":1.140276143},
{"learn":[0.2423387399],"iteration":638,"passed_time":2.012931512,"remaining_time":1.13719605},
{"learn":[0.2422301117],"iteration":639,"passed_time":2.015757958,"remaining_time":1.133863851},
{"learn":[0.2420075942],"iteration":640,"passed_time":2.018634005,"remaining_time":1.130561011},
{"learn":[0.241826027],"iteration":641,"passed_time":2.02150175,"remaining_time":1.12725487},
{"learn":[0.2416837318],"iteration":642,"passed_time":2.024412273,"remaining_time":1.123973844},
{"learn":[0.2416324457],"iteration":643,"passed_time":2.028132831,"remaining_time":1.121141752},
{"learn":[0.2414929879],"iteration":644,"passed_time":2.031345527,"remaining_time":1.118027383},
{"learn":[0.2412800908],"iteration":645,"passed_time":2.034217921,"remaining_time":1.114726229},
{"learn":[0.2410668974],"iteration":646,"passed_time":2.037054622,"remaining_time":1.111406927},
{"learn":[0.2409560542],"iteration":647,"passed_time":2.040086938,"remaining_time":1.108195374},
{"learn":[0.2408375275],"iteration":648,"passed_time":2.043581077,"remaining_time":1.105234142},
{"learn":[0.2406922974],"iteration":649,"passed_time":2.046514866,"remaining_time":1.101969543},
{"learn":[0.2406024371],"iteration":650,"passed_time":2.049439528,"remaining_time":1.098701068},
{"learn":[0.2403093831],"iteration":651,"passed_time":2.052592319,"remaining_time":1.095555409},
{"learn":[0.2401743154],"iteration":652,"passed_time":2.05572759,"remaining_time":1.092400419},
{"learn":[0.2400436309],"iteration":653,"passed_time":2.059181347,"remaining_time":1.089413985},
{"learn":[0.2398497688],"iteration":654,"passed_time":2.062379672,"remaining_time":1.086291583},
{"learn":[0.239745663],"iteration":655,"passed_time":2.065198632,"remaining_time":1.082970014},
{"learn":[0.2396166552],"iteration":656,"passed_time":2.068139746,"remaining_time":1.079713749},
{"learn":[0.2394068666],"iteration":657,"passed_time":2.071200542,"remaining_time":1.076520646},
{"learn":[0.2392980103],"iteration":658,"passed_time":2.074174794,"remaining_time":1.073283163},
{"learn":[0.2391559471],"iteration":659,"passed_time":2.077567638,"remaining_time":1.070262116},
{"learn":[0.2390194992],"iteration":660,"passed_time":2.080660594,"remaining_time":1.067086144},
{"learn":[0.2389051505],"iteration":661,"passed_time":2.083653956,"remaining_time":1.063859573},
{"learn":[0.2387886821],"iteration":662,"passed_time":2.086514587,"remaining_time":1.060566238},
{"learn":[0.2386276007],"iteration":663,"passed_time":2.089388129,"remaining_time":1.05728074},
{"learn":[0.2384331397],"iteration":664,"passed_time":2.092607235,"remaining_time":1.054170562},
{"learn":[0.2383307682],"iteration":665,"passed_time":2.09569211,"remaining_time":1.05099274},
{"learn":[0.2382208117],"iteration":666,"passed_time":2.09865328,"remaining_time":1.047753437},
{"learn":[0.238055807],"iteration":667,"passed_time":2.101697914,"remaining_time":1.044556448},
{"learn":[0.2379410251],"iteration":668,"passed_time":2.104520314,"remaining_time":1.041249961},
{"learn":[0.2377792731],"iteration":669,"passed_time":2.107847307,"remaining_time":1.03819345},
{"learn":[0.2375793614],"iteration":670,"passed_time":2.110891337,"remaining_time":1.034997392},
{"learn":[0.2374515902],"iteration":671,"passed_time":2.113849146,"remaining_time":1.031759702},
{"learn":[0.2373236554],"iteration":672,"passed_time":2.117044293,"remaining_time":1.028638163},
{"learn":[0.2371832644],"iteration":673,"passed_time":2.119855574,"remaining_time":1.025330738},
{"learn":[0.2370365797],"iteration":674,"passed_time":2.123045205,"remaining_time":1.022206951},
{"learn":[0.2368960222],"iteration":675,"passed_time":2.126478131,"remaining_time":1.019199577},
{"learn":[0.2367568735],"iteration":676,"passed_time":2.129479342,"remaining_time":1.015984974},
{"learn":[0.2366455412],"iteration":677,"passed_time":2.132331339,"remaining_time":1.012700134},
{"learn":[0.2364756185],"iteration":678,"passed_time":2.135190439,"remaining_time":1.009419928},
{"learn":[0.2363519873],"iteration":679,"passed_time":2.138099413,"remaining_time":1.00616443},
{"learn":[0.2362136648],"iteration":680,"passed_time":2.141513401,"remaining_time":1.003146512},
{"learn":[0.2360967176],"iteration":681,"passed_time":2.144382655,"remaining_time":0.9998734375},
{"learn":[0.2359387687],"iteration":682,"passed_time":2.147252946,"remaining_time":0.9966020263},
{"learn":[0.2357887184],"iteration":683,"passed_time":2.150103604,"remaining_time":0.9933227178},
{"learn":[0.2356614225],"iteration":684,"passed_time":2.15293478,"remaining_time":0.990035702},
{"learn":[0.2355153828],"iteration":685,"passed_time":2.156373996,"remaining_time":0.9870283304},
{"learn":[0.2354187352],"iteration":686,"passed_time":2.159303085,"remaining_time":0.983787286},
{"learn":[0.2352813241],"iteration":687,"passed_time":2.162270031,"remaining_time":0.9805643165},
{"learn":[0.2350737734],"iteration":688,"passed_time":2.165279927,"remaining_time":0.9773614763},
{"learn":[0.2349972559],"iteration":689,"passed_time":2.168147108,"remaining_time":0.9740950776},
{"learn":[0.2348690588],"iteration":690,"passed_time":2.171419438,"remaining_time":0.9710110077},
{"learn":[0.2347612889],"iteration":691,"passed_time":2.174279867,"remaining_time":0.9677430623},
{"learn":[0.2345925381],"iteration":692,"passed_time":2.177157333,"remaining_time":0.9644838403},
{"learn":[0.234500577],"iteration":693,"passed_time":2.179951417,"remaining_time":0.9611889533},
{"learn":[0.2343985437],"iteration":694,"passed_time":2.182732338,"remaining_time":0.9578897311},
{"learn":[0.2342272429],"iteration":695,"passed_time":2.185670615,"remaining_time":0.9546607284},
{"learn":[0.2340777182],"iteration":696,"passed_time":2.188930124,"remaining_time":0.9515722062},
{"learn":[0.2339353301],"iteration":697,"passed_time":2.1918586,"remaining_time":0.9483399674},
{"learn":[0.2337896558],"iteration":698,"passed_time":2.194782125,"remaining_time":0.9451064657},
{"learn":[0.2336417835],"iteration":699,"passed_time":2.197708115,"remaining_time":0.9418749063},
{"learn":[0.2334518406],"iteration":700,"passed_time":2.200681119,"remaining_time":0.9386642719},
{"learn":[0.2332898891],"iteration":701,"passed_time":2.204338822,"remaining_time":0.9357449702},
{"learn":[0.233189174],"iteration":702,"passed_time":2.207333835,"remaining_time":0.9325435973},
{"learn":[0.2330810042],"iteration":703,"passed_time":2.210667468,"remaining_time":0.9294851856},
{"learn":[0.2329897733],"iteration":704,"passed_time":2.213645545,"remaining_time":0.9262772138},
{"learn":[0.2327594607],"iteration":705,"passed_time":2.21692032,"remaining_time":0.9231934479},
{"learn":[0.232624242],"iteration":706,"passed_time":2.221047786,"remaining_time":0.9204625197},
{"learn":[0.2324916063],"iteration":707,"passed_time":2.224838614,"remaining_time":0.917588807},
{"learn":[0.232350965],"iteration":708,"passed_time":2.227959234,"remaining_time":0.9144374289},
{"learn":[0.2322013087],"iteration":709,"passed_time":2.231106228,"remaining_time":0.9112969101},
{"learn":[0.2320844267],"iteration":710,"passed_time":2.234181806,"remaining_time":0.9081273443},
{"learn":[0.231917169],"iteration":711,"passed_time":2.237536692,"remaining_time":0.9050710216},
{"learn":[0.2317746538],"iteration":712,"passed_time":2.240724251,"remaining_time":0.9019465078},
{"learn":[0.2315824662],"iteration":713,"passed_time":2.243813081,"remaining_time":0.8987822706},
{"learn":[0.2314810499],"iteration":714,"passed_time":2.246862635,"remaining_time":0.8956025889},
{"learn":[0.2313977517],"iteration":715,"passed_time":2.249927737,"remaining_time":0.8924294375},
{"learn":[0.2312437583],"iteration":716,"passed_time":2.253048537,"remaining_time":0.8892785717},
{"learn":[0.2310973493],"iteration":717,"passed_time":2.256063142,"remaining_time":0.886086081},
{"learn":[0.2309226057],"iteration":718,"passed_time":2.259082165,"remaining_time":0.8828958114},
{"learn":[0.2307774438],"iteration":719,"passed_time":2.262246981,"remaining_time":0.8797627149},
{"learn":[0.2305789459],"iteration":720,"passed_time":2.265430776,"remaining_time":0.8766368746},
{"learn":[0.2304271209],"iteration":721,"passed_time":2.268865,"remaining_time":0.8736072992},
{"learn":[0.2303060915],"iteration":722,"passed_time":2.272004075,"remaining_time":0.8704635253},
{"learn":[0.2301668338],"iteration":723,"passed_time":2.275079531,"remaining_time":0.8672955118},
{"learn":[0.2299569158],"iteration":724,"passed_time":2.278232926,"remaining_time":0.8641573168},
{"learn":[0.2298783061],"iteration":725,"passed_time":2.281446377,"remaining_time":0.8610417455},
{"learn":[0.2297521268],"iteration":726,"passed_time":2.284935102,"remaining_time":0.8580292751},
{"learn":[0.229596361],"iteration":727,"passed_time":2.288037316,"remaining_time":0.854871085},
{"learn":[0.2294908987],"iteration":728,"passed_time":2.291126287,"remaining_time":0.8517081259},
{"learn":[0.2293662168],"iteration":729,"passed_time":2.294261367,"remaining_time":0.8485624233},
{"learn":[0.2292314617],"iteration":730,"passed_time":2.297159402,"remaining_time":0.8453295201},
{"learn":[0.2290763059],"iteration":731,"passed_time":2.300794554,"remaining_time":0.8423674051},
{"learn":[0.2289306647],"iteration":732,"passed_time":2.304005278,"remaining_time":0.8392488529},
{"learn":[0.2288270113],"iteration":733,"passed_time":2.307513022,"remaining_time":0.8362376893},
{"learn":[0.2286554357],"iteration":734,"passed_time":2.310709436,"remaining_time":0.8331129261},
{"learn":[0.2285364887],"iteration":735,"passed_time":2.31391051,"remaining_time":0.8299896393},
{"learn":[0.2283287045],"iteration":736,"passed_time":2.317626006,"remaining_time":0.8270497143},
{"learn":[0.2281816144],"iteration":737,"passed_time":2.321041029,"remaining_time":0.8240010158},
{"learn":[0.2280468265],"iteration":738,"passed_time":2.324271165,"remaining_time":0.8208860272},
{"learn":[0.2279434656],"iteration":739,"passed_time":2.327344297,"remaining_time":0.8177155638},
{"learn":[0.2278230284],"iteration":740,"passed_time":2.33058364,"remaining_time":0.8146034585},
{"learn":[0.2276642415],"iteration":741,"passed_time":2.333938023,"remaining_time":0.8115310107},
{"learn":[0.2275338635],"iteration":742,"passed_time":2.337459484,"remaining_time":0.8085155954},
{"learn":[0.2273985792],"iteration":743,"passed_time":2.340646207,"remaining_time":0.8053836411},
{"learn":[0.2272952463],"iteration":744,"passed_time":2.343956766,"remaining_time":0.8022939266},
{"learn":[0.2271278092],"iteration":745,"passed_time":2.34754099,"remaining_time":0.799296798},
{"learn":[0.2269951253],"iteration":746,"passed_time":2.351093484,"remaining_time":0.7962873514},
{"learn":[0.2268670804],"iteration":747,"passed_time":2.354363308,"remaining_time":0.7931812215},
{"learn":[0.2267563344],"iteration":748,"passed_time":2.357958561,"remaining_time":0.79018371},
{"learn":[0.2266341048],"iteration":749,"passed_time":2.361106784,"remaining_time":0.7870355946},
{"learn":[0.2264431396],"iteration":750,"passed_time":2.364474541,"remaining_time":0.7839602671},
{"learn":[0.2263472333],"iteration":751,"passed_time":2.367706045,"remaining_time":0.7808392275},
{"learn":[0.2262012499],"iteration":752,"passed_time":2.371036036,"remaining_time":0.7777502004},
{"learn":[0.2260897459],"iteration":753,"passed_time":2.37434423,"remaining_time":0.7746534224},
{"learn":[0.2259693122],"iteration":754,"passed_time":2.377524754,"remaining_time":0.7715146554},
{"learn":[0.225816988],"iteration":755,"passed_time":2.381140104,"remaining_time":0.7685161181},
{"learn":[0.2256873811],"iteration":756,"passed_time":2.384362148,"remaining_time":0.7653896986},
{"learn":[0.2255811681],"iteration":757,"passed_time":2.387659675,"remaining_time":0.7622871258},
{"learn":[0.2254281744],"iteration":758,"passed_time":2.390913509,"remaining_time":0.7591701655},
{"learn":[0.2252580276],"iteration":759,"passed_time":2.394218504,"remaining_time":0.7560690012},
{"learn":[0.2251209148],"iteration":760,"passed_time":2.397712159,"remaining_time":0.753026552},
{"learn":[0.22496667],"iteration":761,"passed_time":2.401017274,"remaining_time":0.7499240304},
{"learn":[0.2248332309],"iteration":762,"passed_time":2.404246202,"remaining_time":0.7467973129},
{"learn":[0.224670629],"iteration":763,"passed_time":2.407424351,"remaining_time":0.7436546425},
{"learn":[0.2245814772],"iteration":764,"passed_time":2.410615502,"remaining_time":0.7405158733},
{"learn":[0.224451648],"iteration":765,"passed_time":2.414680468,"remaining_time":0.7376439028},
{"learn":[0.224342943],"iteration":766,"passed_time":2.417979293,"remaining_time":0.7345360825},
{"learn":[0.2241960478],"iteration":767,"passed_time":2.421214792,"remaining_time":0.7314086351},
{"learn":[0.224109791],"iteration":768,"passed_time":2.424554474,"remaining_time":0.7283122023},
{"learn":[0.2240410011],"iteration":769,"passed_time":2.427794692,"remaining_time":0.7251854275},
{"learn":[0.2239000599],"iteration":770,"passed_time":2.43162695,"remaining_time":0.7222342042},
{"learn":[0.2237528932],"iteration":771,"passed_time":2.434829045,"remaining_time":0.7190945884},
{"learn":[0.2236636034],"iteration":772,"passed_time":2.438148711,"remaining_time":0.7159893369},
{"learn":[0.2235081281],"iteration":773,"passed_time":2.441231232,"remaining_time":0.7128142873},
{"learn":[0.2233798507],"iteration":774,"passed_time":2.444955084,"remaining_time":0.7098256697},
{"learn":[0.223229469],"iteration":775,"passed_time":2.448201874,"remaining_time":0.7066974482},
{"learn":[0.2230883354],"iteration":776,"passed_time":2.451567357,"remaining_time":0.7036029867},
{"learn":[0.2229732768],"iteration":777,"passed_time":2.454549398,"remaining_time":0.7003984145},
{"learn":[0.2227623664],"iteration":778,"passed_time":2.457856346,"remaining_time":0.6972865884},
{"learn":[0.2226938554],"iteration":779,"passed_time":2.461483755,"remaining_time":0.6942646488},
{"learn":[0.2225701079],"iteration":780,"passed_time":2.464760739,"remaining_time":0.691142896},
{"learn":[0.2224415736],"iteration":781,"passed_time":2.467894334,"remaining_time":0.6879807734},
{"learn":[0.2223294648],"iteration":782,"passed_time":2.471060392,"remaining_time":0.6848277205},
{"learn":[0.2221814464],"iteration":783,"passed_time":2.474534451,"remaining_time":0.6817594917},
{"learn":[0.222086027],"iteration":784,"passed_time":2.478126639,"remaining_time":0.6787225827},
{"learn":[0.222005135],"iteration":785,"passed_time":2.481569849,"remaining_time":0.6756436995},
{"learn":[0.2218877544],"iteration":786,"passed_time":2.484777947,"remaining_time":0.6725002575},
{"learn":[0.2217777242],"iteration":787,"passed_time":2.487976061,"remaining_time":0.6693539658},
{"learn":[0.2216650192],"iteration":788,"passed_time":2.491277443,"remaining_time":0.6662351591},
{"learn":[0.2214498022],"iteration":789,"passed_time":2.49482868,"remaining_time":0.6631823073},
{"learn":[0.2213281303],"iteration":790,"passed_time":2.498024456,"remaining_time":0.6600342747},
{"learn":[0.2212438577],"iteration":791,"passed_time":2.501434462,"remaining_time":0.656942384},
{"learn":[0.2211471151],"iteration":792,"passed_time":2.504818119,"remaining_time":0.653842813},
{"learn":[0.2210208539],"iteration":793,"passed_time":2.508567487,"remaining_time":0.6508374086},
{"learn":[0.2208470225],"iteration":794,"passed_time":2.51203026,"remaining_time":0.6477562306},
{"learn":[0.2206924193],"iteration":795,"passed_time":2.515445778,"remaining_time":0.6446619832},
{"learn":[0.2206017803],"iteration":796,"passed_time":2.518602704,"remaining_time":0.641501065},
{"learn":[0.2204674436],"iteration":797,"passed_time":2.522260458,"remaining_time":0.638466933},
{"learn":[0.2203360262],"iteration":798,"passed_time":2.525360891,"remaining_time":0.6352910376},
{"learn":[0.2202655234],"iteration":799,"passed_time":2.528409096,"remaining_time":0.6321022741},
{"learn":[0.220149698],"iteration":800,"passed_time":2.531715147,"remaining_time":0.6289779204},
{"learn":[0.2200538218],"iteration":801,"passed_time":2.534896608,"remaining_time":0.6258223545},
{"learn":[0.2198643257],"iteration":802,"passed_time":2.538213512,"remaining_time":0.6226999525},
{"learn":[0.2197646669],"iteration":803,"passed_time":2.541556449,"remaining_time":0.619583413},
{"learn":[0.2196625189],"iteration":804,"passed_time":2.544613258,"remaining_time":0.6163970005},
{"learn":[0.2195270202],"iteration":805,"passed_time":2.547684368,"remaining_time":0.6132143516},
{"learn":[0.2193284469],"iteration":806,"passed_time":2.550757348,"remaining_time":0.6100324265},
{"learn":[0.2191937904],"iteration":807,"passed_time":2.55409705,"remaining_time":0.6069141506},
{"learn":[0.2190503334],"iteration":808,"passed_time":2.557577141,"remaining_time":0.6038284721},
{"learn":[0.2189494058],"iteration":809,"passed_time":2.560704855,"remaining_time":0.6006591636},
{"learn":[0.2188392423],"iteration":810,"passed_time":2.563909189,"remaining_time":0.5975078135},
{"learn":[0.2187222513],"iteration":811,"passed_time":2.567180351,"remaining_time":0.5943718053},
{"learn":[0.2185861806],"iteration":812,"passed_time":2.570348468,"remaining_time":0.5912117631},
{"learn":[0.2183604143],"iteration":813,"passed_time":2.574064839,"remaining_time":0.5881769779},
{"learn":[0.2181650649],"iteration":814,"passed_time":2.577274033,"remaining_time":0.585025394},
{"learn":[0.2180529838],"iteration":815,"passed_time":2.580373067,"remaining_time":0.5818488289},
{"learn":[0.2178801665],"iteration":816,"passed_time":2.583691073,"remaining_time":0.578721501},
{"learn":[0.2177619663],"iteration":817,"passed_time":2.586708033,"remaining_time":0.5755267261},
{"learn":[0.2176274781],"iteration":818,"passed_time":2.590041113,"remaining_time":0.5724022484},
{"learn":[0.2175261059],"iteration":819,"passed_time":2.593150874,"remaining_time":0.5692282407},
{"learn":[0.2173627426],"iteration":820,"passed_time":2.596212012,"remaining_time":0.5660437882},
{"learn":[0.2172571549],"iteration":821,"passed_time":2.599077241,"remaining_time":0.5628172128},
{"learn":[0.2171442634],"iteration":822,"passed_time":2.601970465,"remaining_time":0.5595975362},
{"learn":[0.216995565],"iteration":823,"passed_time":2.605334741,"remaining_time":0.5564792652},
{"learn":[0.2168754474],"iteration":824,"passed_time":2.608291524,"remaining_time":0.5532739597},
{"learn":[0.2167735632],"iteration":825,"passed_time":2.611188109,"remaining_time":0.5500565751},
{"learn":[0.2166665277],"iteration":826,"passed_time":2.614099589,"remaining_time":0.546843082},
{"learn":[0.2165361742],"iteration":827,"passed_time":2.617029483,"remaining_time":0.5436341438},
{"learn":[0.2164721499],"iteration":828,"passed_time":2.619900117,"remaining_time":0.540413655},
{"learn":[0.2163388528],"iteration":829,"passed_time":2.623452873,"remaining_time":0.5373337209},
{"learn":[0.2162359145],"iteration":830,"passed_time":2.626600713,"remaining_time":0.5341703013},
{"learn":[0.2161136164],"iteration":831,"passed_time":2.629537501,"remaining_time":0.5309643031},
{"learn":[0.2159318812],"iteration":832,"passed_time":2.632502636,"remaining_time":0.5277646341},
{"learn":[0.2158086574],"iteration":833,"passed_time":2.635403368,"remaining_time":0.5245527087},
{"learn":[0.2157138629],"iteration":834,"passed_time":2.638868545,"remaining_time":0.5214530658},
{"learn":[0.2156210832],"iteration":835,"passed_time":2.642403339,"remaining_time":0.5183662052},
{"learn":[0.2154432497],"iteration":836,"passed_time":2.645427242,"remaining_time":0.5151787819},
{"learn":[0.2152664096],"iteration":837,"passed_time":2.648358777,"remaining_time":0.5119738925},
{"learn":[0.2152051086],"iteration":838,"passed_time":2.651118163,"remaining_time":0.5087366201},
{"learn":[0.2150780545],"iteration":839,"passed_time":2.654411384,"remaining_time":0.5056021684},
{"learn":[0.2149276737],"iteration":840,"passed_time":2.657741546,"remaining_time":0.5024743232},
{"learn":[0.2147949947],"iteration":841,"passed_time":2.661302081,"remaining_time":0.4993892266},
{"learn":[0.2147090427],"iteration":842,"passed_time":2.664629215,"remaining_time":0.4962595335},
{"learn":[0.2146344013],"iteration":843,"passed_time":2.667574736,"remaining_time":0.4930588375},
{"learn":[0.2144772779],"iteration":844,"passed_time":2.671026721,"remaining_time":0.4899516471},
{"learn":[0.2143454228],"iteration":845,"passed_time":2.674018786,"remaining_time":0.4867599208},
{"learn":[0.2142268379],"iteration":846,"passed_time":2.677001028,"remaining_time":0.4835668917},
{"learn":[0.2140593483],"iteration":847,"passed_time":2.679979175,"remaining_time":0.4803736256},
{"learn":[0.2139693688],"iteration":848,"passed_time":2.682854698,"remaining_time":0.4771626142},
{"learn":[0.2138927849],"iteration":849,"passed_time":2.686268415,"remaining_time":0.4740473673},
{"learn":[0.2138228428],"iteration":850,"passed_time":2.68913785,"remaining_time":0.4708361218},
{"learn":[0.213643787],"iteration":851,"passed_time":2.692093536,"remaining_time":0.4676406611},
{"learn":[0.213565468],"iteration":852,"passed_time":2.694887247,"remaining_time":0.4644178491},
{"learn":[0.2134019299],"iteration":853,"passed_time":2.697743832,"remaining_time":0.461206791},
{"learn":[0.2132859652],"iteration":854,"passed_time":2.700983346,"remaining_time":0.4580615032},
{"learn":[0.213179354],"iteration":855,"passed_time":2.704534151,"remaining_time":0.4549683619},
{"learn":[0.2130933443],"iteration":856,"passed_time":2.707503341,"remaining_time":0.4517771036},
{"learn":[0.212989835],"iteration":857,"passed_time":2.710366085,"remaining_time":0.448568746},
{"learn":[0.2128372959],"iteration":858,"passed_time":2.713212255,"remaining_time":0.4453584726},
{"learn":[0.2127226616],"iteration":859,"passed_time":2.716057539,"remaining_time":0.4421489017},
{"learn":[0.2125625914],"iteration":860,"passed_time":2.719425478,"remaining_time":0.4390245545},
{"learn":[0.2124917209],"iteration":861,"passed_time":2.722355,"remaining_time":0.4358294548},
{"learn":[0.2123846976],"iteration":862,"passed_time":2.725172319,"remaining_time":0.4326171585},
{"learn":[0.2121976837],"iteration":863,"passed_time":2.728115789,"remaining_time":0.4294256334},
{"learn":[0.2120768999],"iteration":864,"passed_time":2.730962522,"remaining_time":0.4262195844},
{"learn":[0.2119790659],"iteration":865,"passed_time":2.734084928,"remaining_time":0.4230570213},
{"learn":[0.2118507408],"iteration":866,"passed_time":2.737688669,"remaining_time":0.4199683886},
{"learn":[0.2117656564],"iteration":867,"passed_time":2.74076326,"remaining_time":0.4167980995},
{"learn":[0.2116610463],"iteration":868,"passed_time":2.743699354,"remaining_time":0.4136071523},
{"learn":[0.2114841461],"iteration":869,"passed_time":2.746686546,"remaining_time":0.4104244265},
{"learn":[0.2113092156],"iteration":870,"passed_time":2.750012532,"remaining_time":0.4072923268},
{"learn":[0.211228441],"iteration":871,"passed_time":2.752961738,"remaining_time":0.4041044752},
{"learn":[0.2110780818],"iteration":872,"passed_time":2.755962909,"remaining_time":0.4009247301},
{"learn":[0.2109618954],"iteration":873,"passed_time":2.758882337,"remaining_time":0.3977336093},
{"learn":[0.2108549872],"iteration":874,"passed_time":2.761708653,"remaining_time":0.3945298076},
{"learn":[0.2107521867],"iteration":875,"passed_time":2.76527274,"remaining_time":0.3914313012},
{"learn":[0.2106331786],"iteration":876,"passed_time":2.768454378,"remaining_time":0.388278094},
{"learn":[0.2105111682],"iteration":877,"passed_time":2.771390149,"remaining_time":0.3850906585},
{"learn":[0.210441887],"iteration":878,"passed_time":2.774156147,"remaining_time":0.3818804252},
{"learn":[0.2102870416],"iteration":879,"passed_time":2.777075254,"remaining_time":0.37869208},
{"learn":[0.2102044034],"iteration":880,"passed_time":2.780009566,"remaining_time":0.3755063999},
{"learn":[0.2100979344],"iteration":881,"passed_time":2.783373509,"remaining_time":0.3723787688},
{"learn":[0.2100059131],"iteration":882,"passed_time":2.786242331,"remaining_time":0.3691849974},
{"learn":[0.2098819023],"iteration":883,"passed_time":2.789028757,"remaining_time":0.3659811491},
{"learn":[0.2097846272],"iteration":884,"passed_time":2.791888079,"remaining_time":0.3627877165},
{"learn":[0.209678786],"iteration":885,"passed_time":2.79499066,"remaining_time":0.3596263378},
{"learn":[0.2095899075],"iteration":886,"passed_time":2.798300605,"remaining_time":0.3564915089},
{"learn":[0.2094613801],"iteration":887,"passed_time":2.801355161,"remaining_time":0.3533240743},
{"learn":[0.2093565253],"iteration":888,"passed_time":2.804250982,"remaining_time":0.3501370742},
{"learn":[0.2092676839],"iteration":889,"passed_time":2.807145947,"remaining_time":0.3469506227},
{"learn":[0.2091419442],"iteration":890,"passed_time":2.810483958,"remaining_time":0.3438190252},
{"learn":[0.2089602439],"iteration":891,"passed_time":2.813691875,"remaining_time":0.3406712135},
{"learn":[0.2087499577],"iteration":892,"passed_time":2.81698744,"remaining_time":0.3375337694},
{"learn":[0.208621657],"iteration":893,"passed_time":2.819870471,"remaining_time":0.334347058},
{"learn":[0.2084703894],"iteration":894,"passed_time":2.822841976,"remaining_time":0.331171405},
{"learn":[0.2083710839],"iteration":895,"passed_time":2.825852999,"remaining_time":0.3280007945},
{"learn":[0.2082767018],"iteration":896,"passed_time":2.828771009,"remaining_time":0.3248198595},
{"learn":[0.2081787357],"iteration":897,"passed_time":2.832103757,"remaining_time":0.3216866183},
{"learn":[0.208115334],"iteration":898,"passed_time":2.835422458,"remaining_time":0.3185513551},
{"learn":[0.2080137914],"iteration":899,"passed_time":2.838284819,"remaining_time":0.3153649799},
{"learn":[0.2079118976],"iteration":900,"passed_time":2.841222181,"remaining_time":0.3121875648},
{"learn":[0.2077947632],"iteration":901,"passed_time":2.844164019,"remaining_time":0.3090111684},
{"learn":[0.207619301],"iteration":902,"passed_time":2.847480275,"remaining_time":0.3058755113},
{"learn":[0.2075249169],"iteration":903,"passed_time":2.850510015,"remaining_time":0.3027090281},
{"learn":[0.2073629904],"iteration":904,"passed_time":2.853398752,"remaining_time":0.2995280457},
{"learn":[0.2072850776],"iteration":905,"passed_time":2.856335871,"remaining_time":0.2963527284},
{"learn":[0.2071795839],"iteration":906,"passed_time":2.859252271,"remaining_time":0.2931758117},
{"learn":[0.2070916344],"iteration":907,"passed_time":2.862765379,"remaining_time":0.2900599282},
{"learn":[0.2069695817],"iteration":908,"passed_time":2.865751827,"remaining_time":0.286890447},
{"learn":[0.2068620829],"iteration":909,"passed_time":2.868608503,"remaining_time":0.2837085333},
{"learn":[0.2067666174],"iteration":910,"passed_time":2.871576315,"remaining_time":0.2805381911},
{"learn":[0.2066678366],"iteration":911,"passed_time":2.874515448,"remaining_time":0.2773655256},
{"learn":[0.2065559861],"iteration":912,"passed_time":2.877733136,"remaining_time":0.2742199154},
{"learn":[0.2064665039],"iteration":913,"passed_time":2.880892337,"remaining_time":0.2710686444},
{"learn":[0.2063751296],"iteration":914,"passed_time":2.883774079,"remaining_time":0.2678915811},
{"learn":[0.2063091613],"iteration":915,"passed_time":2.886714489,"remaining_time":0.2647205427},
{"learn":[0.2062205297],"iteration":916,"passed_time":2.889732265,"remaining_time":0.2615570098},
{"learn":[0.2061766061],"iteration":917,"passed_time":2.892573655,"remaining_time":0.2583780389},
{"learn":[0.2060713673],"iteration":918,"passed_time":2.895850739,"remaining_time":0.2552382044},
{"learn":[0.2059939558],"iteration":919,"passed_time":2.898619313,"remaining_time":0.2520538533},
{"learn":[0.2058191752],"iteration":920,"passed_time":2.901588977,"remaining_time":0.2488876538},
{"learn":[0.2056943019],"iteration":921,"passed_time":2.90449961,"remaining_time":0.2457168868},
{"learn":[0.2056096712],"iteration":922,"passed_time":2.907282836,"remaining_time":0.2425360546},
{"learn":[0.205490206],"iteration":923,"passed_time":2.910651051,"remaining_time":0.239404199},
{"learn":[0.2053642379],"iteration":924,"passed_time":2.913650239,"remaining_time":0.2362419113},
{"learn":[0.2052783728],"iteration":925,"passed_time":2.916592099,"remaining_time":0.2330753945},
{"learn":[0.205184877],"iteration":926,"passed_time":2.919527206,"remaining_time":0.2299088307},
{"learn":[0.2051093674],"iteration":927,"passed_time":2.922412058,"remaining_time":0.2267388666},
{"learn":[0.2049782181],"iteration":928,"passed_time":2.925520054,"remaining_time":0.2235865703},
{"learn":[0.2048402995],"iteration":929,"passed_time":2.928725047,"remaining_time":0.2204416702},
{"learn":[0.2047144375],"iteration":930,"passed_time":2.931648642,"remaining_time":0.2172757855},
{"learn":[0.2046074172],"iteration":931,"passed_time":2.934597566,"remaining_time":0.2141122687},
{"learn":[0.2044478719],"iteration":932,"passed_time":2.937445215,"remaining_time":0.2109419393},
{"learn":[0.2042979413],"iteration":933,"passed_time":2.940536058,"remaining_time":0.2077894859},
{"learn":[0.2041577278],"iteration":934,"passed_time":2.944018217,"remaining_time":0.204664368},
{"learn":[0.2040575807],"iteration":935,"passed_time":2.947475298,"remaining_time":0.2015367725},
{"learn":[0.2039778844],"iteration":936,"passed_time":2.950386566,"remaining_time":0.1983717755},
{"learn":[0.2038891484],"iteration":937,"passed_time":2.953191296,"remaining_time":0.1952002776},
{"learn":[0.2037853942],"iteration":938,"passed_time":2.956107012,"remaining_time":0.1920367707},
{"learn":[0.2036812341],"iteration":939,"passed_time":2.959551853,"remaining_time":0.1889075651},
{"learn":[0.203575524],"iteration":940,"passed_time":2.962524047,"remaining_time":0.185748054},
{"learn":[0.2034517527],"iteration":941,"passed_time":2.965437006,"remaining_time":0.1825852934},
{"learn":[0.2033166428],"iteration":942,"passed_time":2.968245168,"remaining_time":0.1794167281},
{"learn":[0.2031674204],"iteration":943,"passed_time":2.971236281,"remaining_time":0.1762597794},
{"learn":[0.2030703519],"iteration":944,"passed_time":2.974591982,"remaining_time":0.1731244011},
{"learn":[0.2029757176],"iteration":945,"passed_time":2.97774734,"remaining_time":0.1699771209},
{"learn":[0.2028061919],"iteration":946,"passed_time":2.980696715,"remaining_time":0.1668182956},
{"learn":[0.2026883693],"iteration":947,"passed_time":2.983655279,"remaining_time":0.1636604162},
{"learn":[0.2025291108],"iteration":948,"passed_time":2.986611277,"remaining_time":0.1605028189},
{"learn":[0.2024155239],"iteration":949,"passed_time":2.989587774,"remaining_time":0.1573467249},
{"learn":[0.2023196137],"iteration":950,"passed_time":2.992878066,"remaining_time":0.1542071769},
{"learn":[0.2022077597],"iteration":951,"passed_time":2.995839015,"remaining_time":0.1510507066},
{"learn":[0.2021108113],"iteration":952,"passed_time":2.998799622,"remaining_time":0.1478946298},
{"learn":[0.2019688073],"iteration":953,"passed_time":3.001774438,"remaining_time":0.1447396479},
{"learn":[0.201895566],"iteration":954,"passed_time":3.004664453,"remaining_time":0.1415810475},
{"learn":[0.2018248043],"iteration":955,"passed_time":3.00811678,"remaining_time":0.1384488894},
{"learn":[0.2017302969],"iteration":956,"passed_time":3.01108428,"remaining_time":0.135294278},
{"learn":[0.2016202908],"iteration":957,"passed_time":3.014043982,"remaining_time":0.1321397153},
{"learn":[0.2015054597],"iteration":958,"passed_time":3.016897568,"remaining_time":0.1289810222},
{"learn":[0.2014138835],"iteration":959,"passed_time":3.019782339,"remaining_time":0.1258242641},
{"learn":[0.201326301],"iteration":960,"passed_time":3.022976056,"remaining_time":0.12268061},
{"learn":[0.2012665081],"iteration":961,"passed_time":3.026355698,"remaining_time":0.119544196},
{"learn":[0.2011247539],"iteration":962,"passed_time":3.029299842,"remaining_time":0.1163905443},
{"learn":[0.2010455014],"iteration":963,"passed_time":3.032557621,"remaining_time":0.1132490398},
{"learn":[0.2009459352],"iteration":964,"passed_time":3.03543556,"remaining_time":0.1100935177},
{"learn":[0.2008572223],"iteration":965,"passed_time":3.039390274,"remaining_time":0.1069764693},
{"learn":[0.200776284],"iteration":966,"passed_time":3.043336979,"remaining_time":0.103857415},
{"learn":[0.2006832322],"iteration":967,"passed_time":3.046346331,"remaining_time":0.1007056638},
{"learn":[0.2005718065],"iteration":968,"passed_time":3.049176319,"remaining_time":0.09754846842},
{"learn":[0.2005125804],"iteration":969,"passed_time":3.052209793,"remaining_time":0.09439824103},
{"learn":[0.2003866821],"iteration":970,"passed_time":3.055597163,"remaining_time":0.09125882361},
{"learn":[0.2002987584],"iteration":971,"passed_time":3.058596946,"remaining_time":0.08810773095},
{"learn":[0.2001549902],"iteration":972,"passed_time":3.06149962,"remaining_time":0.08495425461},
{"learn":[0.2000740913],"iteration":973,"passed_time":3.064388819,"remaining_time":0.08180093358},
{"learn":[0.1999759672],"iteration":974,"passed_time":3.06738516,"remaining_time":0.07865090154},
{"learn":[0.1998533571],"iteration":975,"passed_time":3.070483067,"remaining_time":0.07550368196},
{"learn":[0.1997758403],"iteration":976,"passed_time":3.073528908,"remaining_time":0.07235533765},
{"learn":[0.1996977867],"iteration":977,"passed_time":3.076494616,"remaining_time":0.06920540036},
{"learn":[0.1996534709],"iteration":978,"passed_time":3.079278254,"remaining_time":0.06605193396},
{"learn":[0.1995675382],"iteration":979,"passed_time":3.082338823,"remaining_time":0.06290487394},
{"learn":[0.1994623172],"iteration":980,"passed_time":3.085135946,"remaining_time":0.05975288784},
{"learn":[0.1993317868],"iteration":981,"passed_time":3.088452265,"remaining_time":0.05661114132},
{"learn":[0.1992850021],"iteration":982,"passed_time":3.091321641,"remaining_time":0.05346131017},
{"learn":[0.1991882724],"iteration":983,"passed_time":3.094152284,"remaining_time":0.05031141924},
{"learn":[0.1990654938],"iteration":984,"passed_time":3.097248833,"remaining_time":0.04716622588},
{"learn":[0.1990009366],"iteration":985,"passed_time":3.100157705,"remaining_time":0.0440184664},
{"learn":[0.198933964],"iteration":986,"passed_time":3.103593881,"remaining_time":0.04087813622},
{"learn":[0.198826766],"iteration":987,"passed_time":3.106393801,"remaining_time":0.03772947937},
{"learn":[0.1987271687],"iteration":988,"passed_time":3.10923656,"remaining_time":0.03458200421},
{"learn":[0.1986656685],"iteration":989,"passed_time":3.11214012,"remaining_time":0.03143575878},
{"learn":[0.1985752533],"iteration":990,"passed_time":3.115062366,"remaining_time":0.02829017285},
{"learn":[0.1985282926],"iteration":991,"passed_time":3.117889306,"remaining_time":0.02514426859},
{"learn":[0.1984344652],"iteration":992,"passed_time":3.1210746,"remaining_time":0.02200153293},
{"learn":[0.1983453756],"iteration":993,"passed_time":3.123977767,"remaining_time":0.01885700865},
{"learn":[0.1982538144],"iteration":994,"passed_time":3.126947642,"remaining_time":0.01571330473},
{"learn":[0.1981553135],"iteration":995,"passed_time":3.129767266,"remaining_time":0.01256934645},
{"learn":[0.1980929778],"iteration":996,"passed_time":3.132649602,"remaining_time":0.009426227489},
{"learn":[0.1979679215],"iteration":997,"passed_time":3.136067202,"remaining_time":0.006284703811},
{"learn":[0.1977818265],"iteration":998,"passed_time":3.139024256,"remaining_time":0.003142166423},
{"learn":[0.197652446],"iteration":999,"passed_time":3.142081106,"remaining_time":0}
]}